[{"teams":["Birmingham","Arsenal"],"score":[2,1],"koef":{"w1":4.13,"w2":3.41,"x":1.77},"date":"15.05.2005"},{"teams":["Bolton","Everton"],"score":[3,2],"koef":{"w1":1.83,"w2":3.33,"x":4.02},"date":"15.05.2005"},{"teams":["Charlton","Crystal Palace"],"score":[2,2],"koef":{"w1":2.67,"w2":3.47,"x":2.29},"date":"15.05.2005"},{"teams":["Fulham","Norwich"],"score":[6,0],"koef":{"w1":2.66,"w2":3.44,"x":2.35},"date":"15.05.2005"},{"teams":["Liverpool","Aston Villa"],"score":[2,1],"koef":{"w1":1.63,"w2":3.41,"x":5.3},"date":"15.05.2005"},{"teams":["Manchester City","Middlesbrough"],"score":[1,1],"koef":{"w1":2.01,"w2":3.14,"x":3.56},"date":"15.05.2005"},{"teams":["Newcastle Utd","Chelsea"],"score":[1,1],"koef":{"w1":3.42,"w2":3.33,"x":1.99},"date":"15.05.2005"},{"teams":["Southampton","Manchester United"],"score":[1,2],"koef":{"w1":2.51,"w2":3.53,"x":2.4},"date":"15.05.2005"},{"teams":["Tottenham","Blackburn"],"score":[0,0],"koef":{"w1":1.52,"w2":3.61,"x":6.08},"date":"15.05.2005"},{"teams":["West Brom","Portsmouth"],"score":[2,0],"koef":{"w1":1.55,"w2":3.76,"x":5.52},"date":"15.05.2005"},{"teams":["Arsenal","Everton"],"score":[7,0],"koef":{"w1":1.47,"w2":3.72,"x":6.6},"date":"11.05.2005"},{"teams":["Manchester United","Chelsea"],"score":[1,3],"koef":{"w1":2.12,"w2":3.18,"x":3.18},"date":"10.05.2005"},{"teams":["Arsenal","Liverpool"],"score":[3,1],"koef":{"w1":1.73,"w2":3.4,"x":4.44},"date":"08.05.2005"},{"teams":["Aston Villa","Manchester City"],"score":[1,2],"koef":{"w1":2.25,"w2":3.24,"x":2.9},"date":"07.05.2005"},{"teams":["Blackburn","Fulham"],"score":[1,3],"koef":{"w1":2,"w2":3.21,"x":3.53},"date":"07.05.2005"},{"teams":["Chelsea","Charlton"],"score":[1,0],"koef":{"w1":1.3,"w2":4.51,"x":9.23},"date":"07.05.2005"},{"teams":["Crystal Palace","Southampton"],"score":[2,2],"koef":{"w1":2.16,"w2":3.26,"x":3.07},"date":"07.05.2005"},{"teams":["Everton","Newcastle Utd"],"score":[2,0],"koef":{"w1":1.69,"w2":3.34,"x":4.82},"date":"07.05.2005"},{"teams":["Manchester United","West Brom"],"score":[1,1],"koef":{"w1":1.29,"w2":4.96,"x":8.94},"date":"07.05.2005"},{"teams":["Middlesbrough","Tottenham"],"score":[1,0],"koef":{"w1":2.25,"w2":3.2,"x":2.96},"date":"07.05.2005"},{"teams":["Norwich","Birmingham"],"score":[1,0],"koef":{"w1":1.85,"w2":3.44,"x":3.78},"date":"07.05.2005"},{"teams":["Portsmouth","Bolton"],"score":[1,1],"koef":{"w1":2.8,"w2":3.25,"x":2.31},"date":"07.05.2005"},{"teams":["Fulham","Newcastle Utd"],"score":[1,3],"koef":{"w1":2.18,"w2":3.19,"x":3.12},"date":"04.05.2005"},{"teams":["West Brom","Arsenal"],"score":[0,2],"koef":{"w1":5.78,"w2":3.58,"x":1.54},"date":"02.05.2005"},{"teams":["Charlton","Manchester United"],"score":[0,4],"koef":{"w1":5.37,"w2":3.55,"x":1.58},"date":"01.05.2005"},{"teams":["Tottenham","Aston Villa"],"score":[5,1],"koef":{"w1":1.91,"w2":3.27,"x":3.8},"date":"01.05.2005"},{"teams":["Birmingham","Blackburn"],"score":[2,1],"koef":{"w1":2.11,"w2":3.19,"x":3.28},"date":"30.04.2005"},{"teams":["Bolton","Chelsea"],"score":[0,2],"koef":{"w1":3.67,"w2":3.23,"x":1.93},"date":"30.04.2005"},{"teams":["Fulham","Everton"],"score":[2,0],"koef":{"w1":2.7,"w2":3.18,"x":2.45},"date":"30.04.2005"},{"teams":["Liverpool","Middlesbrough"],"score":[1,1],"koef":{"w1":1.69,"w2":3.39,"x":4.86},"date":"30.04.2005"},{"teams":["Manchester City","Portsmouth"],"score":[2,0],"koef":{"w1":1.76,"w2":3.32,"x":4.44},"date":"30.04.2005"},{"teams":["Newcastle Utd","Crystal Palace"],"score":[0,0],"koef":{"w1":1.81,"w2":3.37,"x":3.95},"date":"30.04.2005"},{"teams":["Southampton","Norwich"],"score":[4,3],"koef":{"w1":2.04,"w2":3.29,"x":3.33},"date":"30.04.2005"},{"teams":["Newcastle Utd","Middlesbrough"],"score":[0,0],"koef":{"w1":2.1,"w2":3.23,"x":3.23},"date":"27.04.2005"},{"teams":["West Brom","Blackburn"],"score":[1,1],"koef":{"w1":2.01,"w2":3.3,"x":3.43},"date":"26.04.2005"},{"teams":["Arsenal","Tottenham"],"score":[1,0],"koef":{"w1":1.46,"w2":3.71,"x":7.05},"date":"25.04.2005"},{"teams":["Manchester United","Newcastle Utd"],"score":[2,1],"koef":{"w1":1.32,"w2":4.48,"x":8.45},"date":"24.04.2005"},{"teams":["Portsmouth","Southampton"],"score":[4,1],"koef":{"w1":2.19,"w2":3.21,"x":3.05},"date":"24.04.2005"},{"teams":["Aston Villa","Bolton"],"score":[1,1],"koef":{"w1":2.29,"w2":3.23,"x":2.87},"date":"23.04.2005"},{"teams":["Blackburn","Manchester City"],"score":[0,0],"koef":{"w1":2.26,"w2":3.22,"x":2.94},"date":"23.04.2005"},{"teams":["Chelsea","Fulham"],"score":[3,1],"koef":{"w1":1.28,"w2":4.72,"x":9.71},"date":"23.04.2005"},{"teams":["Crystal Palace","Liverpool"],"score":[1,0],"koef":{"w1":3.68,"w2":3.4,"x":1.89},"date":"23.04.2005"},{"teams":["Everton","Birmingham"],"score":[1,1],"koef":{"w1":1.64,"w2":3.38,"x":5.36},"date":"23.04.2005"},{"teams":["Middlesbrough","West Brom"],"score":[4,0],"koef":{"w1":1.93,"w2":3.28,"x":3.69},"date":"23.04.2005"},{"teams":["Norwich","Charlton"],"score":[1,0],"koef":{"w1":2.16,"w2":3.34,"x":3.03},"date":"23.04.2005"},{"teams":["Aston Villa","Charlton"],"score":[0,0],"koef":{"w1":1.86,"w2":3.25,"x":4.06},"date":"20.04.2005"},{"teams":["Blackburn","Crystal Palace"],"score":[1,0],"koef":{"w1":1.86,"w2":3.3,"x":3.97},"date":"20.04.2005"},{"teams":["Chelsea","Arsenal"],"score":[0,0],"koef":{"w1":2.03,"w2":3.18,"x":3.5},"date":"20.04.2005"},{"teams":["Everton","Manchester United"],"score":[1,0],"koef":{"w1":4.45,"w2":3.33,"x":1.76},"date":"20.04.2005"},{"teams":["Manchester City","Birmingham"],"score":[3,0],"koef":{"w1":1.95,"w2":3.26,"x":3.66},"date":"20.04.2005"},{"teams":["Norwich","Newcastle Utd"],"score":[2,1],"koef":{"w1":2.38,"w2":3.3,"x":2.72},"date":"20.04.2005"},{"teams":["Portsmouth","Liverpool"],"score":[1,2],"koef":{"w1":3.31,"w2":3.25,"x":2.06},"date":"20.04.2005"},{"teams":["Tottenham","West Brom"],"score":[1,1],"koef":{"w1":1.68,"w2":3.44,"x":4.84},"date":"20.04.2005"},{"teams":["Bolton","Southampton"],"score":[1,1],"koef":{"w1":1.6,"w2":3.53,"x":5.36},"date":"19.04.2005"},{"teams":["Middlesbrough","Fulham"],"score":[1,1],"koef":{"w1":1.79,"w2":3.33,"x":4.3},"date":"19.04.2005"},{"teams":["Birmingham","Portsmouth"],"score":[0,0],"koef":{"w1":1.83,"w2":3.27,"x":4.13},"date":"16.04.2005"},{"teams":["Charlton","Bolton"],"score":[1,2],"koef":{"w1":2.52,"w2":3.18,"x":2.59},"date":"16.04.2005"},{"teams":["Crystal Palace","Norwich"],"score":[3,3],"koef":{"w1":2,"w2":3.23,"x":3.5},"date":"16.04.2005"},{"teams":["Fulham","Manchester City"],"score":[1,1],"koef":{"w1":2.35,"w2":3.2,"x":2.81},"date":"16.04.2005"},{"teams":["Liverpool","Tottenham"],"score":[2,2],"koef":{"w1":1.72,"w2":3.4,"x":4.6},"date":"16.04.2005"},{"teams":["Southampton","Aston Villa"],"score":[2,3],"koef":{"w1":2.08,"w2":3.22,"x":3.32},"date":"16.04.2005"},{"teams":["Aston Villa","West Brom"],"score":[1,1],"koef":{"w1":1.83,"w2":3.26,"x":4.21},"date":"10.04.2005"},{"teams":["Everton","Crystal Palace"],"score":[4,0],"koef":{"w1":1.64,"w2":3.37,"x":5.35},"date":"10.04.2005"},{"teams":["Tottenham","Newcastle Utd"],"score":[1,0],"koef":{"w1":1.97,"w2":3.23,"x":3.65},"date":"10.04.2005"},{"teams":["Blackburn","Southampton"],"score":[3,0],"koef":{"w1":2.02,"w2":3.17,"x":3.55},"date":"09.04.2005"},{"teams":["Bolton","Fulham"],"score":[3,1],"koef":{"w1":1.72,"w2":3.34,"x":4.7},"date":"09.04.2005"},{"teams":["Chelsea","Birmingham"],"score":[1,1],"koef":{"w1":1.25,"w2":4.96,"x":9.93},"date":"09.04.2005"},{"teams":["Manchester City","Liverpool"],"score":[1,0],"koef":{"w1":2.74,"w2":3.18,"x":2.42},"date":"09.04.2005"},{"teams":["Middlesbrough","Arsenal"],"score":[0,1],"koef":{"w1":4.93,"w2":3.34,"x":1.69},"date":"09.04.2005"},{"teams":["Norwich","Manchester United"],"score":[2,0],"koef":{"w1":8.61,"w2":4.17,"x":1.36},"date":"09.04.2005"},{"teams":["Portsmouth","Charlton"],"score":[4,2],"koef":{"w1":2.26,"w2":3.19,"x":2.97},"date":"09.04.2005"},{"teams":["Fulham","Portsmouth"],"score":[3,1],"koef":{"w1":2.06,"w2":3.2,"x":3.39},"date":"03.04.2005"},{"teams":["West Brom","Everton"],"score":[1,0],"koef":{"w1":2.66,"w2":3.18,"x":2.46},"date":"03.04.2005"},{"teams":["Arsenal","Norwich"],"score":[4,1],"koef":{"w1":1.17,"w2":5.8,"x":9.99},"date":"02.04.2005"},{"teams":["Birmingham","Tottenham"],"score":[1,1],"koef":{"w1":2.3,"w2":3.18,"x":2.92},"date":"02.04.2005"},{"teams":["Charlton","Manchester City"],"score":[2,2],"koef":{"w1":2.07,"w2":3.2,"x":3.35},"date":"02.04.2005"},{"teams":["Crystal Palace","Middlesbrough"],"score":[0,1],"koef":{"w1":2.37,"w2":3.19,"x":2.77},"date":"02.04.2005"},{"teams":["Liverpool","Bolton"],"score":[1,0],"koef":{"w1":1.82,"w2":3.23,"x":4.29},"date":"02.04.2005"},{"teams":["Manchester United","Blackburn"],"score":[0,0],"koef":{"w1":1.25,"w2":4.94,"x":10.26},"date":"02.04.2005"},{"teams":["Newcastle Utd","Aston Villa"],"score":[0,3],"koef":{"w1":1.65,"w2":3.39,"x":5.13},"date":"02.04.2005"},{"teams":["Southampton","Chelsea"],"score":[1,3],"koef":{"w1":6.09,"w2":3.5,"x":1.54},"date":"02.04.2005"},{"teams":["Birmingham","Aston Villa"],"score":[2,0],"koef":{"w1":2.3,"w2":3.04,"x":3.04},"date":"20.03.2005"},{"teams":["Liverpool","Everton"],"score":[2,1],"koef":{"w1":1.83,"w2":3.16,"x":4.36},"date":"20.03.2005"},{"teams":["Middlesbrough","Southampton"],"score":[1,3],"koef":{"w1":1.98,"w2":3.18,"x":3.62},"date":"20.03.2005"},{"teams":["Blackburn","Arsenal"],"score":[0,1],"koef":{"w1":4.26,"w2":3.28,"x":1.81},"date":"19.03.2005"},{"teams":["Bolton","Norwich"],"score":[1,0],"koef":{"w1":1.55,"w2":3.53,"x":6.08},"date":"19.03.2005"},{"teams":["Charlton","West Brom"],"score":[1,4],"koef":{"w1":1.66,"w2":3.41,"x":5.08},"date":"19.03.2005"},{"teams":["Chelsea","Crystal Palace"],"score":[4,1],"koef":{"w1":1.19,"w2":5.65,"x":9.99},"date":"19.03.2005"},{"teams":["Manchester United","Fulham"],"score":[1,0],"koef":{"w1":1.23,"w2":5.2,"x":10.34},"date":"19.03.2005"},{"teams":["Portsmouth","Newcastle Utd"],"score":[1,1],"koef":{"w1":2.75,"w2":3.16,"x":2.43},"date":"19.03.2005"},{"teams":["Tottenham","Manchester City"],"score":[2,1],"koef":{"w1":1.82,"w2":3.24,"x":4.23},"date":"19.03.2005"},{"teams":["Liverpool","Blackburn"],"score":[0,0],"koef":{"w1":1.54,"w2":3.54,"x":6.21},"date":"16.03.2005"},{"teams":["Charlton","Tottenham"],"score":[2,0],"koef":{"w1":2.32,"w2":3.2,"x":2.84},"date":"16.03.2005"},{"teams":["Chelsea","West Brom"],"score":[1,0],"koef":{"w1":1.15,"w2":6.07,"x":9.99},"date":"15.03.2005"},{"teams":["Manchester City","Bolton"],"score":[0,1],"koef":{"w1":2.31,"w2":3.15,"x":2.9},"date":"07.03.2005"},{"teams":["Everton","Blackburn"],"score":[0,1],"koef":{"w1":1.73,"w2":3.3,"x":4.8},"date":"06.03.2005"},{"teams":["West Brom","Birmingham"],"score":[2,0],"koef":{"w1":2.61,"w2":3.09,"x":2.58},"date":"06.03.2005"},{"teams":["Arsenal","Portsmouth"],"score":[3,0],"koef":{"w1":1.34,"w2":4.27,"x":8.92},"date":"05.03.2005"},{"teams":["Aston Villa","Middlesbrough"],"score":[2,0],"koef":{"w1":2.25,"w2":3.19,"x":2.98},"date":"05.03.2005"},{"teams":["Crystal Palace","Manchester United"],"score":[0,0],"koef":{"w1":7.16,"w2":3.79,"x":1.45},"date":"05.03.2005"},{"teams":["Fulham","Charlton"],"score":[0,0],"koef":{"w1":2.27,"w2":3.18,"x":2.96},"date":"05.03.2005"},{"teams":["Newcastle Utd","Liverpool"],"score":[1,0],"koef":{"w1":2.34,"w2":3.18,"x":2.85},"date":"05.03.2005"},{"teams":["Norwich","Chelsea"],"score":[1,3],"koef":{"w1":8.33,"w2":3.99,"x":1.38},"date":"05.03.2005"},{"teams":["Southampton","Tottenham"],"score":[1,0],"koef":{"w1":2.47,"w2":3.18,"x":2.69},"date":"05.03.2005"},{"teams":["Norwich","Manchester City"],"score":[2,3],"koef":{"w1":2.67,"w2":3.14,"x":2.53},"date":"28.02.2005"},{"teams":["Middlesbrough","Charlton"],"score":[2,2],"koef":{"w1":1.9,"w2":3.22,"x":3.92},"date":"27.02.2005"},{"teams":["Newcastle Utd","Bolton"],"score":[2,1],"koef":{"w1":1.87,"w2":3.27,"x":3.97},"date":"27.02.2005"},{"teams":["Aston Villa","Everton"],"score":[1,3],"koef":{"w1":2.19,"w2":3.16,"x":3.12},"date":"26.02.2005"},{"teams":["Crystal Palace","Birmingham"],"score":[2,0],"koef":{"w1":2.49,"w2":3.18,"x":2.65},"date":"26.02.2005"},{"teams":["Manchester United","Portsmouth"],"score":[2,1],"koef":{"w1":1.21,"w2":5.41,"x":9.99},"date":"26.02.2005"},{"teams":["Southampton","Arsenal"],"score":[1,1],"koef":{"w1":5.74,"w2":3.54,"x":1.57},"date":"26.02.2005"},{"teams":["Tottenham","Fulham"],"score":[2,0],"koef":{"w1":1.79,"w2":3.27,"x":4.41},"date":"26.02.2005"},{"teams":["West Brom","Southampton"],"score":[0,0],"koef":{"w1":2.25,"w2":3.2,"x":2.96},"date":"22.02.2005"},{"teams":["Arsenal","Crystal Palace"],"score":[5,1],"koef":{"w1":1.2,"w2":5.52,"x":9.99},"date":"14.02.2005"},{"teams":["Manchester City","Manchester United"],"score":[0,2],"koef":{"w1":4.69,"w2":3.25,"x":1.75},"date":"13.02.2005"},{"teams":["Birmingham","Liverpool"],"score":[2,0],"koef":{"w1":3.21,"w2":3.19,"x":2.14},"date":"12.02.2005"},{"teams":["Blackburn","Norwich"],"score":[3,0],"koef":{"w1":1.76,"w2":3.26,"x":4.66},"date":"12.02.2005"},{"teams":["Bolton","Middlesbrough"],"score":[0,0],"koef":{"w1":2.05,"w2":3.19,"x":3.41},"date":"12.02.2005"},{"teams":["Everton","Chelsea"],"score":[0,1],"koef":{"w1":4.51,"w2":3.25,"x":1.78},"date":"12.02.2005"},{"teams":["Portsmouth","Aston Villa"],"score":[1,2],"koef":{"w1":2.22,"w2":3.21,"x":3.03},"date":"12.02.2005"},{"teams":["Chelsea","Manchester City"],"score":[0,0],"koef":{"w1":1.24,"w2":5.15,"x":9.84},"date":"06.02.2005"},{"teams":["Southampton","Everton"],"score":[2,2],"koef":{"w1":2.59,"w2":3.19,"x":2.56},"date":"06.02.2005"},{"teams":["Aston Villa","Arsenal"],"score":[1,3],"koef":{"w1":4.36,"w2":3.34,"x":1.78},"date":"05.02.2005"},{"teams":["Crystal Palace","Bolton"],"score":[0,1],"koef":{"w1":2.54,"w2":3.19,"x":2.59},"date":"05.02.2005"},{"teams":["Liverpool","Fulham"],"score":[3,1],"koef":{"w1":1.46,"w2":3.73,"x":7.13},"date":"05.02.2005"},{"teams":["Manchester United","Birmingham"],"score":[2,0],"koef":{"w1":1.25,"w2":5.02,"x":9.89},"date":"05.02.2005"},{"teams":["Middlesbrough","Blackburn"],"score":[1,0],"koef":{"w1":1.91,"w2":3.17,"x":3.93},"date":"05.02.2005"},{"teams":["Newcastle Utd","Charlton"],"score":[1,1],"koef":{"w1":1.76,"w2":3.37,"x":4.41},"date":"05.02.2005"},{"teams":["Norwich","West Brom"],"score":[3,2],"koef":{"w1":2.21,"w2":3.18,"x":3.08},"date":"05.02.2005"},{"teams":["Tottenham","Portsmouth"],"score":[3,1],"koef":{"w1":1.69,"w2":3.39,"x":4.85},"date":"05.02.2005"},{"teams":["Birmingham","Southampton"],"score":[2,1],"koef":{"w1":1.86,"w2":3.29,"x":3.93},"date":"02.02.2005"},{"teams":["Blackburn","Chelsea"],"score":[0,1],"koef":{"w1":6.87,"w2":3.78,"x":1.46},"date":"02.02.2005"},{"teams":["Everton","Norwich"],"score":[1,0],"koef":{"w1":1.53,"w2":3.58,"x":6.19},"date":"02.02.2005"},{"teams":["Fulham","Aston Villa"],"score":[1,1],"koef":{"w1":2.26,"w2":3.18,"x":2.96},"date":"02.02.2005"},{"teams":["Manchester City","Newcastle Utd"],"score":[1,1],"koef":{"w1":2.32,"w2":3.22,"x":2.85},"date":"02.02.2005"},{"teams":["Arsenal","Manchester United"],"score":[2,4],"koef":{"w1":2.29,"w2":3.12,"x":3.09},"date":"01.02.2005"},{"teams":["Bolton","Tottenham"],"score":[3,1],"koef":{"w1":2.21,"w2":3.23,"x":3.04},"date":"01.02.2005"},{"teams":["Charlton","Liverpool"],"score":[1,2],"koef":{"w1":2.76,"w2":3.2,"x":2.38},"date":"01.02.2005"},{"teams":["Portsmouth","Middlesbrough"],"score":[2,1],"koef":{"w1":2.48,"w2":3.22,"x":2.65},"date":"01.02.2005"},{"teams":["West Brom","Crystal Palace"],"score":[2,2],"koef":{"w1":2.24,"w2":3.22,"x":2.97},"date":"01.02.2005"},{"teams":["Blackburn","Bolton"],"score":[0,1],"koef":{"w1":2.25,"w2":3.15,"x":3.03},"date":"24.01.2005"},{"teams":["Arsenal","Newcastle Utd"],"score":[1,0],"koef":{"w1":1.44,"w2":3.83,"x":7.41},"date":"23.01.2005"},{"teams":["Birmingham","Fulham"],"score":[1,2],"koef":{"w1":1.89,"w2":3.22,"x":3.96},"date":"22.01.2005"},{"teams":["Chelsea","Portsmouth"],"score":[3,0],"koef":{"w1":1.19,"w2":5.76,"x":9.91},"date":"22.01.2005"},{"teams":["Crystal Palace","Tottenham"],"score":[3,0],"koef":{"w1":3.09,"w2":3.23,"x":2.18},"date":"22.01.2005"},{"teams":["Everton","Charlton"],"score":[0,1],"koef":{"w1":1.84,"w2":3.25,"x":4.15},"date":"22.01.2005"},{"teams":["Manchester United","Aston Villa"],"score":[3,1],"koef":{"w1":1.31,"w2":4.47,"x":9.08},"date":"22.01.2005"},{"teams":["Norwich","Middlesbrough"],"score":[4,4],"koef":{"w1":3.02,"w2":3.21,"x":2.22},"date":"22.01.2005"},{"teams":["Southampton","Liverpool"],"score":[2,0],"koef":{"w1":4.39,"w2":3.28,"x":1.79},"date":"22.01.2005"},{"teams":["West Brom","Manchester City"],"score":[2,0],"koef":{"w1":2.99,"w2":3.21,"x":2.24},"date":"22.01.2005"},{"teams":["Fulham","West Brom"],"score":[1,0],"koef":{"w1":1.76,"w2":3.22,"x":4.75},"date":"16.01.2005"},{"teams":["Middlesbrough","Everton"],"score":[1,1],"koef":{"w1":2.01,"w2":3.19,"x":3.52},"date":"16.01.2005"},{"teams":["Aston Villa","Norwich"],"score":[3,0],"koef":{"w1":1.66,"w2":3.35,"x":5.25},"date":"15.01.2005"},{"teams":["Bolton","Arsenal"],"score":[1,0],"koef":{"w1":5.74,"w2":3.51,"x":1.58},"date":"15.01.2005"},{"teams":["Charlton","Birmingham"],"score":[3,1],"koef":{"w1":2.08,"w2":3.15,"x":3.4},"date":"15.01.2005"},{"teams":["Liverpool","Manchester United"],"score":[0,1],"koef":{"w1":2.62,"w2":3.08,"x":2.61},"date":"15.01.2005"},{"teams":["Manchester City","Crystal Palace"],"score":[3,1],"koef":{"w1":1.63,"w2":3.44,"x":5.26},"date":"15.01.2005"},{"teams":["Newcastle Utd","Southampton"],"score":[2,1],"koef":{"w1":1.54,"w2":3.55,"x":6.11},"date":"15.01.2005"},{"teams":["Portsmouth","Blackburn"],"score":[0,1],"koef":{"w1":2.04,"w2":3.19,"x":3.47},"date":"15.01.2005"},{"teams":["Tottenham","Chelsea"],"score":[0,2],"koef":{"w1":4.26,"w2":3.27,"x":1.81},"date":"15.01.2005"},{"teams":["Southampton","Fulham"],"score":[3,3],"koef":{"w1":2.33,"w2":3.21,"x":2.82},"date":"05.01.2005"},{"teams":["Arsenal","Manchester City"],"score":[1,1],"koef":{"w1":1.27,"w2":4.88,"x":9.68},"date":"04.01.2005"},{"teams":["Birmingham","Bolton"],"score":[1,2],"koef":{"w1":1.84,"w2":3.26,"x":4.13},"date":"04.01.2005"},{"teams":["Chelsea","Middlesbrough"],"score":[2,0],"koef":{"w1":1.33,"w2":4.34,"x":8.94},"date":"04.01.2005"},{"teams":["Everton","Portsmouth"],"score":[2,1],"koef":{"w1":1.75,"w2":3.29,"x":4.56},"date":"04.01.2005"},{"teams":["Manchester United","Tottenham"],"score":[0,0],"koef":{"w1":1.41,"w2":4.01,"x":7.44},"date":"04.01.2005"},{"teams":["Blackburn","Charlton"],"score":[1,0],"koef":{"w1":2.26,"w2":3.21,"x":2.95},"date":"03.01.2005"},{"teams":["Crystal Palace","Aston Villa"],"score":[2,0],"koef":{"w1":2.68,"w2":3.19,"x":2.44},"date":"03.01.2005"},{"teams":["Norwich","Liverpool"],"score":[1,2],"koef":{"w1":5.43,"w2":3.41,"x":1.64},"date":"03.01.2005"},{"teams":["West Brom","Newcastle Utd"],"score":[0,0],"koef":{"w1":4.01,"w2":3.26,"x":1.85},"date":"03.01.2005"},{"teams":["Aston Villa","Blackburn"],"score":[1,0],"koef":{"w1":1.86,"w2":3.27,"x":4.05},"date":"01.01.2005"},{"teams":["Bolton","West Brom"],"score":[1,1],"koef":{"w1":1.61,"w2":3.42,"x":5.62},"date":"01.01.2005"},{"teams":["Charlton","Arsenal"],"score":[1,3],"koef":{"w1":5.99,"w2":3.48,"x":1.56},"date":"01.01.2005"},{"teams":["Fulham","Crystal Palace"],"score":[3,1],"koef":{"w1":1.94,"w2":3.24,"x":3.73},"date":"01.01.2005"},{"teams":["Liverpool","Chelsea"],"score":[0,1],"koef":{"w1":3.03,"w2":3.19,"x":2.22},"date":"01.01.2005"},{"teams":["Manchester City","Southampton"],"score":[2,1],"koef":{"w1":1.7,"w2":3.36,"x":4.79},"date":"01.01.2005"},{"teams":["Middlesbrough","Manchester United"],"score":[0,2],"koef":{"w1":3.41,"w2":3.23,"x":2.04},"date":"01.01.2005"},{"teams":["Newcastle Utd","Birmingham"],"score":[2,1],"koef":{"w1":1.87,"w2":3.26,"x":3.99},"date":"01.01.2005"},{"teams":["Portsmouth","Norwich"],"score":[1,1],"koef":{"w1":1.63,"w2":3.41,"x":5.36},"date":"01.01.2005"},{"teams":["Tottenham","Everton"],"score":[5,2],"koef":{"w1":2.21,"w2":3.17,"x":3.08},"date":"01.01.2005"},{"teams":["Newcastle Utd","Arsenal"],"score":[0,1],"koef":{"w1":4.44,"w2":3.37,"x":1.73},"date":"29.12.2004"},{"teams":["Aston Villa","Manchester United"],"score":[0,1],"koef":{"w1":4.32,"w2":3.35,"x":1.76},"date":"28.12.2004"},{"teams":["Bolton","Blackburn"],"score":[0,1],"koef":{"w1":1.95,"w2":3.22,"x":3.59},"date":"28.12.2004"},{"teams":["Charlton","Everton"],"score":[2,0],"koef":{"w1":2.47,"w2":3.11,"x":2.65},"date":"28.12.2004"},{"teams":["Fulham","Birmingham"],"score":[2,3],"koef":{"w1":2.31,"w2":3.19,"x":2.81},"date":"28.12.2004"},{"teams":["Liverpool","Southampton"],"score":[1,0],"koef":{"w1":1.33,"w2":4.17,"x":8.63},"date":"28.12.2004"},{"teams":["Manchester City","West Brom"],"score":[1,1],"koef":{"w1":1.48,"w2":3.64,"x":6.59},"date":"28.12.2004"},{"teams":["Middlesbrough","Norwich"],"score":[2,0],"koef":{"w1":1.44,"w2":3.71,"x":7.01},"date":"28.12.2004"},{"teams":["Portsmouth","Chelsea"],"score":[0,2],"koef":{"w1":6.1,"w2":3.59,"x":1.51},"date":"28.12.2004"},{"teams":["Tottenham","Crystal Palace"],"score":[1,1],"koef":{"w1":1.51,"w2":3.6,"x":6.13},"date":"28.12.2004"},{"teams":["Arsenal","Fulham"],"score":[2,0],"koef":{"w1":1.24,"w2":5,"x":9.58},"date":"26.12.2004"},{"teams":["Birmingham","Middlesbrough"],"score":[2,0],"koef":{"w1":2.5,"w2":3.11,"x":2.66},"date":"26.12.2004"},{"teams":["Blackburn","Newcastle Utd"],"score":[2,2],"koef":{"w1":2.57,"w2":3.12,"x":2.58},"date":"26.12.2004"},{"teams":["Chelsea","Aston Villa"],"score":[1,0],"koef":{"w1":1.27,"w2":4.66,"x":9.29},"date":"26.12.2004"},{"teams":["Crystal Palace","Portsmouth"],"score":[0,1],"koef":{"w1":2.43,"w2":3.12,"x":2.73},"date":"26.12.2004"},{"teams":["Everton","Manchester City"],"score":[2,1],"koef":{"w1":1.87,"w2":3.25,"x":3.9},"date":"26.12.2004"},{"teams":["Manchester United","Bolton"],"score":[2,0],"koef":{"w1":1.31,"w2":4.48,"x":8.7},"date":"26.12.2004"},{"teams":["Norwich","Tottenham"],"score":[0,2],"koef":{"w1":2.86,"w2":3.17,"x":2.31},"date":"26.12.2004"},{"teams":["Southampton","Charlton"],"score":[0,0],"koef":{"w1":2.38,"w2":3.12,"x":2.8},"date":"26.12.2004"},{"teams":["West Brom","Liverpool"],"score":[0,5],"koef":{"w1":5.17,"w2":3.47,"x":1.63},"date":"26.12.2004"},{"teams":["Charlton","Fulham"],"score":[2,1],"koef":{"w1":2,"w2":3.16,"x":3.48},"date":"20.12.2004"},{"teams":["Liverpool","Newcastle Utd"],"score":[3,1],"koef":{"w1":1.82,"w2":3.24,"x":4.02},"date":"19.12.2004"},{"teams":["Portsmouth","Arsenal"],"score":[0,1],"koef":{"w1":5.61,"w2":3.57,"x":1.55},"date":"19.12.2004"},{"teams":["Birmingham","West Brom"],"score":[4,0],"koef":{"w1":1.77,"w2":3.23,"x":4.32},"date":"18.12.2004"},{"teams":["Blackburn","Everton"],"score":[0,0],"koef":{"w1":2.79,"w2":3.1,"x":2.36},"date":"18.12.2004"},{"teams":["Bolton","Manchester City"],"score":[0,1],"koef":{"w1":2.12,"w2":3.14,"x":3.19},"date":"18.12.2004"},{"teams":["Chelsea","Norwich"],"score":[4,0],"koef":{"w1":1.17,"w2":5.64,"x":10.05},"date":"18.12.2004"},{"teams":["Manchester United","Crystal Palace"],"score":[5,2],"koef":{"w1":1.21,"w2":5.21,"x":9.73},"date":"18.12.2004"},{"teams":["Middlesbrough","Aston Villa"],"score":[3,0],"koef":{"w1":1.95,"w2":3.15,"x":3.64},"date":"18.12.2004"},{"teams":["Tottenham","Southampton"],"score":[5,1],"koef":{"w1":1.76,"w2":3.28,"x":4.28},"date":"18.12.2004"},{"teams":["Liverpool","Portsmouth"],"score":[1,1],"koef":{"w1":1.42,"w2":3.81,"x":7.18},"date":"14.12.2004"},{"teams":["Fulham","Manchester United"],"score":[1,1],"koef":{"w1":5.98,"w2":3.65,"x":1.52},"date":"13.12.2004"},{"teams":["Arsenal","Chelsea"],"score":[2,2],"koef":{"w1":2.42,"w2":3.04,"x":2.83},"date":"12.12.2004"},{"teams":["Aston Villa","Birmingham"],"score":[1,2],"koef":{"w1":1.92,"w2":3.15,"x":3.94},"date":"12.12.2004"},{"teams":["Crystal Palace","Blackburn"],"score":[0,0],"koef":{"w1":2.3,"w2":3.14,"x":2.89},"date":"11.12.2004"},{"teams":["Everton","Liverpool"],"score":[1,0],"koef":{"w1":2.54,"w2":3.1,"x":2.61},"date":"11.12.2004"},{"teams":["Manchester City","Tottenham"],"score":[0,1],"koef":{"w1":2.14,"w2":3.16,"x":3.15},"date":"11.12.2004"},{"teams":["Newcastle Utd","Portsmouth"],"score":[1,1],"koef":{"w1":1.59,"w2":3.52,"x":5.46},"date":"11.12.2004"},{"teams":["Norwich","Bolton"],"score":[3,2],"koef":{"w1":2.59,"w2":3.06,"x":2.57},"date":"11.12.2004"},{"teams":["Southampton","Middlesbrough"],"score":[2,2],"koef":{"w1":2.77,"w2":3.16,"x":2.39},"date":"11.12.2004"},{"teams":["West Brom","Charlton"],"score":[0,1],"koef":{"w1":2.5,"w2":3.12,"x":2.64},"date":"11.12.2004"},{"teams":["Middlesbrough","Manchester City"],"score":[3,2],"koef":{"w1":1.85,"w2":3.24,"x":3.92},"date":"06.12.2004"},{"teams":["Crystal Palace","Charlton"],"score":[0,1],"koef":{"w1":2.38,"w2":3.13,"x":2.75},"date":"05.12.2004"},{"teams":["Arsenal","Birmingham"],"score":[3,0],"koef":{"w1":1.31,"w2":4.51,"x":8.51},"date":"04.12.2004"},{"teams":["Aston Villa","Liverpool"],"score":[1,1],"koef":{"w1":2.4,"w2":3.13,"x":2.73},"date":"04.12.2004"},{"teams":["Blackburn","Tottenham"],"score":[0,1],"koef":{"w1":2.36,"w2":3.12,"x":2.78},"date":"04.12.2004"},{"teams":["Chelsea","Newcastle Utd"],"score":[4,0],"koef":{"w1":1.45,"w2":3.74,"x":6.73},"date":"04.12.2004"},{"teams":["Everton","Bolton"],"score":[3,2],"koef":{"w1":2.01,"w2":3.14,"x":3.5},"date":"04.12.2004"},{"teams":["Manchester United","Southampton"],"score":[3,0],"koef":{"w1":1.22,"w2":5.17,"x":9.76},"date":"04.12.2004"},{"teams":["Norwich","Fulham"],"score":[0,1],"koef":{"w1":2.34,"w2":3.1,"x":2.84},"date":"04.12.2004"},{"teams":["Portsmouth","West Brom"],"score":[3,2],"koef":{"w1":1.81,"w2":3.24,"x":4.16},"date":"04.12.2004"},{"teams":["Liverpool","Arsenal"],"score":[2,1],"koef":{"w1":3.21,"w2":3.19,"x":2.09},"date":"28.11.2004"},{"teams":["Newcastle Utd","Everton"],"score":[1,1],"koef":{"w1":1.87,"w2":3.21,"x":4},"date":"28.11.2004"},{"teams":["Tottenham","Middlesbrough"],"score":[2,0],"koef":{"w1":2.45,"w2":3.14,"x":2.67},"date":"28.11.2004"},{"teams":["Birmingham","Norwich"],"score":[1,1],"koef":{"w1":1.77,"w2":3.25,"x":4.4},"date":"27.11.2004"},{"teams":["Bolton","Portsmouth"],"score":[0,1],"koef":{"w1":1.6,"w2":3.42,"x":5.41},"date":"27.11.2004"},{"teams":["Charlton","Chelsea"],"score":[0,4],"koef":{"w1":5.64,"w2":3.47,"x":1.57},"date":"27.11.2004"},{"teams":["Fulham","Blackburn"],"score":[0,2],"koef":{"w1":1.87,"w2":3.23,"x":3.88},"date":"27.11.2004"},{"teams":["Manchester City","Aston Villa"],"score":[2,0],"koef":{"w1":2.28,"w2":3.18,"x":2.87},"date":"27.11.2004"},{"teams":["Southampton","Crystal Palace"],"score":[2,2],"koef":{"w1":2.01,"w2":3.16,"x":3.48},"date":"27.11.2004"},{"teams":["West Brom","Manchester United"],"score":[0,3],"koef":{"w1":6.19,"w2":3.62,"x":1.51},"date":"27.11.2004"},{"teams":["Aston Villa","Tottenham"],"score":[1,0],"koef":{"w1":1.91,"w2":3.21,"x":3.74},"date":"22.11.2004"},{"teams":["Blackburn","Birmingham"],"score":[3,3],"koef":{"w1":2.31,"w2":3.13,"x":2.87},"date":"21.11.2004"},{"teams":["Arsenal","West Brom"],"score":[1,1],"koef":{"w1":1.17,"w2":5.72,"x":9.84},"date":"20.11.2004"},{"teams":["Chelsea","Bolton"],"score":[2,2],"koef":{"w1":1.35,"w2":4.15,"x":8.34},"date":"20.11.2004"},{"teams":["Crystal Palace","Newcastle Utd"],"score":[0,2],"koef":{"w1":2.87,"w2":3.16,"x":2.27},"date":"20.11.2004"},{"teams":["Everton","Fulham"],"score":[1,0],"koef":{"w1":1.8,"w2":3.22,"x":4.27},"date":"20.11.2004"},{"teams":["Manchester United","Charlton"],"score":[2,0],"koef":{"w1":1.33,"w2":4.26,"x":8.58},"date":"20.11.2004"},{"teams":["Middlesbrough","Liverpool"],"score":[2,0],"koef":{"w1":2.43,"w2":3.14,"x":2.71},"date":"20.11.2004"},{"teams":["Norwich","Southampton"],"score":[2,1],"koef":{"w1":2.3,"w2":3.16,"x":2.86},"date":"20.11.2004"},{"teams":["Portsmouth","Manchester City"],"score":[1,3],"koef":{"w1":2.21,"w2":3.17,"x":3},"date":"20.11.2004"},{"teams":["Newcastle Utd","Manchester United"],"score":[1,3],"koef":{"w1":3.03,"w2":3.19,"x":2.18},"date":"14.11.2004"},{"teams":["West Brom","Middlesbrough"],"score":[1,2],"koef":{"w1":2.9,"w2":3.15,"x":2.27},"date":"14.11.2004"},{"teams":["Birmingham","Everton"],"score":[0,1],"koef":{"w1":2.33,"w2":3.13,"x":2.83},"date":"13.11.2004"},{"teams":["Bolton","Aston Villa"],"score":[1,2],"koef":{"w1":2.13,"w2":3.19,"x":3.16},"date":"13.11.2004"},{"teams":["Charlton","Norwich"],"score":[4,0],"koef":{"w1":1.8,"w2":3.26,"x":4.15},"date":"13.11.2004"},{"teams":["Fulham","Chelsea"],"score":[1,4],"koef":{"w1":5.57,"w2":3.39,"x":1.6},"date":"13.11.2004"},{"teams":["Liverpool","Crystal Palace"],"score":[3,2],"koef":{"w1":1.43,"w2":3.83,"x":6.93},"date":"13.11.2004"},{"teams":["Manchester City","Blackburn"],"score":[1,1],"koef":{"w1":1.82,"w2":3.28,"x":4.09},"date":"13.11.2004"},{"teams":["Southampton","Portsmouth"],"score":[2,1],"koef":{"w1":2.36,"w2":3.13,"x":2.78},"date":"13.11.2004"},{"teams":["Tottenham","Arsenal"],"score":[4,5],"koef":{"w1":4.77,"w2":3.3,"x":1.7},"date":"13.11.2004"},{"teams":["Manchester United","Manchester City"],"score":[0,0],"koef":{"w1":1.43,"w2":3.81,"x":7.35},"date":"07.11.2004"},{"teams":["Middlesbrough","Bolton"],"score":[1,1],"koef":{"w1":1.95,"w2":3.21,"x":3.6},"date":"07.11.2004"},{"teams":["Newcastle Utd","Fulham"],"score":[1,4],"koef":{"w1":1.55,"w2":3.52,"x":5.85},"date":"07.11.2004"},{"teams":["Aston Villa","Portsmouth"],"score":[3,0],"koef":{"w1":1.81,"w2":3.28,"x":4.12},"date":"06.11.2004"},{"teams":["Chelsea","Everton"],"score":[1,0],"koef":{"w1":1.4,"w2":3.94,"x":7.2},"date":"06.11.2004"},{"teams":["Crystal Palace","Arsenal"],"score":[1,1],"koef":{"w1":6.98,"w2":4,"x":1.41},"date":"06.11.2004"},{"teams":["Liverpool","Birmingham"],"score":[0,1],"koef":{"w1":1.47,"w2":3.73,"x":6.58},"date":"06.11.2004"},{"teams":["Norwich","Blackburn"],"score":[1,1],"koef":{"w1":2.24,"w2":3.18,"x":2.93},"date":"06.11.2004"},{"teams":["Southampton","West Brom"],"score":[2,2],"koef":{"w1":1.9,"w2":3.21,"x":3.8},"date":"06.11.2004"},{"teams":["Tottenham","Charlton"],"score":[2,3],"koef":{"w1":1.88,"w2":3.23,"x":3.83},"date":"06.11.2004"},{"teams":["Manchester City","Norwich"],"score":[1,1],"koef":{"w1":1.67,"w2":3.36,"x":4.83},"date":"01.11.2004"},{"teams":["Bolton","Newcastle Utd"],"score":[2,1],"koef":{"w1":2.43,"w2":3.13,"x":2.71},"date":"31.10.2004"},{"teams":["Arsenal","Southampton"],"score":[2,2],"koef":{"w1":1.17,"w2":5.74,"x":9.99},"date":"30.10.2004"},{"teams":["Birmingham","Crystal Palace"],"score":[0,1],"koef":{"w1":1.76,"w2":3.29,"x":4.33},"date":"30.10.2004"},{"teams":["Blackburn","Liverpool"],"score":[2,2],"koef":{"w1":4.17,"w2":3.23,"x":1.81},"date":"30.10.2004"},{"teams":["Charlton","Middlesbrough"],"score":[1,2],"koef":{"w1":2.4,"w2":3.16,"x":2.73},"date":"30.10.2004"},{"teams":["Everton","Aston Villa"],"score":[1,1],"koef":{"w1":2.07,"w2":3.15,"x":3.33},"date":"30.10.2004"},{"teams":["Fulham","Tottenham"],"score":[2,0],"koef":{"w1":2.51,"w2":3.1,"x":2.63},"date":"30.10.2004"},{"teams":["Portsmouth","Manchester United"],"score":[2,0],"koef":{"w1":5.02,"w2":3.37,"x":1.66},"date":"30.10.2004"},{"teams":["West Brom","Chelsea"],"score":[1,4],"koef":{"w1":7.5,"w2":3.78,"x":1.41},"date":"30.10.2004"},{"teams":["Manchester United","Arsenal"],"score":[2,0],"koef":{"w1":2.5,"w2":3.11,"x":2.65},"date":"24.10.2004"},{"teams":["Middlesbrough","Portsmouth"],"score":[1,1],"koef":{"w1":1.66,"w2":3.38,"x":4.97},"date":"24.10.2004"},{"teams":["Newcastle Utd","Manchester City"],"score":[4,3],"koef":{"w1":1.68,"w2":3.41,"x":4.73},"date":"24.10.2004"},{"teams":["Southampton","Birmingham"],"score":[0,0],"koef":{"w1":2.39,"w2":3.14,"x":2.71},"date":"24.10.2004"},{"teams":["Aston Villa","Fulham"],"score":[2,0],"koef":{"w1":1.76,"w2":3.28,"x":4.38},"date":"23.10.2004"},{"teams":["Chelsea","Blackburn"],"score":[4,0],"koef":{"w1":1.28,"w2":4.64,"x":9.03},"date":"23.10.2004"},{"teams":["Crystal Palace","West Brom"],"score":[3,0],"koef":{"w1":2.28,"w2":3.14,"x":2.89},"date":"23.10.2004"},{"teams":["Liverpool","Charlton"],"score":[2,0],"koef":{"w1":1.49,"w2":3.65,"x":6.46},"date":"23.10.2004"},{"teams":["Norwich","Everton"],"score":[2,3],"koef":{"w1":2.67,"w2":3.06,"x":2.5},"date":"23.10.2004"},{"teams":["Tottenham","Bolton"],"score":[1,2],"koef":{"w1":1.91,"w2":3.22,"x":3.72},"date":"23.10.2004"},{"teams":["Portsmouth","Tottenham"],"score":[1,0],"koef":{"w1":2.61,"w2":3.13,"x":2.53},"date":"18.10.2004"},{"teams":["Charlton","Newcastle Utd"],"score":[1,1],"koef":{"w1":2.73,"w2":3.09,"x":2.43},"date":"17.10.2004"},{"teams":["Arsenal","Aston Villa"],"score":[3,1],"koef":{"w1":1.28,"w2":4.64,"x":9.18},"date":"16.10.2004"},{"teams":["Birmingham","Manchester United"],"score":[0,0],"koef":{"w1":4.83,"w2":3.33,"x":1.7},"date":"16.10.2004"},{"teams":["Blackburn","Middlesbrough"],"score":[0,4],"koef":{"w1":2.47,"w2":3.11,"x":2.68},"date":"16.10.2004"},{"teams":["Bolton","Crystal Palace"],"score":[1,0],"koef":{"w1":1.59,"w2":3.49,"x":5.37},"date":"16.10.2004"},{"teams":["Everton","Southampton"],"score":[1,0],"koef":{"w1":1.7,"w2":3.31,"x":4.73},"date":"16.10.2004"},{"teams":["Fulham","Liverpool"],"score":[2,4],"koef":{"w1":3.2,"w2":3.15,"x":2.12},"date":"16.10.2004"},{"teams":["Manchester City","Chelsea"],"score":[1,0],"koef":{"w1":4.65,"w2":3.33,"x":1.7},"date":"16.10.2004"},{"teams":["West Brom","Norwich"],"score":[0,0],"koef":{"w1":2.09,"w2":3.13,"x":3.29},"date":"16.10.2004"},{"teams":["Crystal Palace","Fulham"],"score":[2,0],"koef":{"w1":2.73,"w2":3.11,"x":2.38},"date":"04.10.2004"},{"teams":["Birmingham","Newcastle Utd"],"score":[2,2],"koef":{"w1":2.62,"w2":3.14,"x":2.49},"date":"03.10.2004"},{"teams":["Chelsea","Liverpool"],"score":[1,0],"koef":{"w1":1.73,"w2":3.26,"x":4.56},"date":"03.10.2004"},{"teams":["Manchester United","Middlesbrough"],"score":[1,1],"koef":{"w1":1.33,"w2":4.17,"x":8.65},"date":"03.10.2004"},{"teams":["Arsenal","Charlton"],"score":[4,0],"koef":{"w1":1.24,"w2":5.08,"x":9.53},"date":"02.10.2004"},{"teams":["Blackburn","Aston Villa"],"score":[2,2],"koef":{"w1":2.38,"w2":3.13,"x":2.77},"date":"02.10.2004"},{"teams":["Everton","Tottenham"],"score":[0,1],"koef":{"w1":2.24,"w2":3.17,"x":2.92},"date":"02.10.2004"},{"teams":["Norwich","Portsmouth"],"score":[2,2],"koef":{"w1":2.32,"w2":3.15,"x":2.82},"date":"02.10.2004"},{"teams":["Southampton","Manchester City"],"score":[0,0],"koef":{"w1":2.34,"w2":3.18,"x":2.77},"date":"02.10.2004"},{"teams":["West Brom","Bolton"],"score":[2,1],"koef":{"w1":2.78,"w2":3.13,"x":2.36},"date":"02.10.2004"},{"teams":["Charlton","Blackburn"],"score":[1,0],"koef":{"w1":1.99,"w2":3.19,"x":3.48},"date":"27.09.2004"},{"teams":["Portsmouth","Everton"],"score":[0,1],"koef":{"w1":2.24,"w2":3.16,"x":2.93},"date":"26.09.2004"},{"teams":["Aston Villa","Crystal Palace"],"score":[1,1],"koef":{"w1":1.45,"w2":3.79,"x":6.78},"date":"25.09.2004"},{"teams":["Bolton","Birmingham"],"score":[1,1],"koef":{"w1":1.93,"w2":3.23,"x":3.61},"date":"25.09.2004"},{"teams":["Fulham","Southampton"],"score":[1,0],"koef":{"w1":1.98,"w2":3.21,"x":3.48},"date":"25.09.2004"},{"teams":["Liverpool","Norwich"],"score":[3,0],"koef":{"w1":1.38,"w2":4.04,"x":7.56},"date":"25.09.2004"},{"teams":["Manchester City","Arsenal"],"score":[0,1],"koef":{"w1":5.17,"w2":3.49,"x":1.61},"date":"25.09.2004"},{"teams":["Middlesbrough","Chelsea"],"score":[0,1],"koef":{"w1":3.22,"w2":3.18,"x":2.08},"date":"25.09.2004"},{"teams":["Newcastle Utd","West Brom"],"score":[3,1],"koef":{"w1":1.45,"w2":3.8,"x":7},"date":"25.09.2004"},{"teams":["Tottenham","Manchester United"],"score":[0,1],"koef":{"w1":3.11,"w2":3.17,"x":2.16},"date":"25.09.2004"},{"teams":["Manchester United","Liverpool"],"score":[2,1],"koef":{"w1":1.97,"w2":3.16,"x":3.56},"date":"20.09.2004"},{"teams":["Chelsea","Tottenham"],"score":[0,0],"koef":{"w1":1.45,"w2":3.71,"x":7.05},"date":"19.09.2004"},{"teams":["Everton","Middlesbrough"],"score":[1,0],"koef":{"w1":2.42,"w2":3.14,"x":2.69},"date":"19.09.2004"},{"teams":["Southampton","Newcastle Utd"],"score":[1,2],"koef":{"w1":2.77,"w2":3.15,"x":2.35},"date":"19.09.2004"},{"teams":["Arsenal","Bolton"],"score":[2,2],"koef":{"w1":1.26,"w2":4.91,"x":9.37},"date":"18.09.2004"},{"teams":["Birmingham","Charlton"],"score":[1,1],"koef":{"w1":1.89,"w2":3.24,"x":3.75},"date":"18.09.2004"},{"teams":["Blackburn","Portsmouth"],"score":[1,0],"koef":{"w1":2.14,"w2":3.16,"x":3.12},"date":"18.09.2004"},{"teams":["Crystal Palace","Manchester City"],"score":[1,2],"koef":{"w1":2.63,"w2":3.17,"x":2.47},"date":"18.09.2004"},{"teams":["Norwich","Aston Villa"],"score":[0,0],"koef":{"w1":2.73,"w2":3.11,"x":2.41},"date":"18.09.2004"},{"teams":["West Brom","Fulham"],"score":[1,1],"koef":{"w1":2.41,"w2":3.16,"x":2.69},"date":"18.09.2004"},{"teams":["Charlton","Southampton"],"score":[0,0],"koef":{"w1":1.91,"w2":3.23,"x":3.73},"date":"13.09.2004"},{"teams":["Tottenham","Norwich"],"score":[0,0],"koef":{"w1":1.58,"w2":3.47,"x":5.61},"date":"12.09.2004"},{"teams":["Aston Villa","Chelsea"],"score":[0,0],"koef":{"w1":3.7,"w2":3.23,"x":1.91},"date":"11.09.2004"},{"teams":["Bolton","Manchester United"],"score":[2,2],"koef":{"w1":3.56,"w2":3.25,"x":1.94},"date":"11.09.2004"},{"teams":["Fulham","Arsenal"],"score":[0,3],"koef":{"w1":6.12,"w2":3.58,"x":1.52},"date":"11.09.2004"},{"teams":["Liverpool","West Brom"],"score":[3,0],"koef":{"w1":1.41,"w2":3.87,"x":7.32},"date":"11.09.2004"},{"teams":["Manchester City","Everton"],"score":[0,1],"koef":{"w1":1.89,"w2":3.23,"x":3.78},"date":"11.09.2004"},{"teams":["Middlesbrough","Birmingham"],"score":[2,1],"koef":{"w1":1.89,"w2":3.21,"x":3.85},"date":"11.09.2004"},{"teams":["Newcastle Utd","Blackburn"],"score":[3,0],"koef":{"w1":1.69,"w2":3.34,"x":4.71},"date":"11.09.2004"},{"teams":["Portsmouth","Crystal Palace"],"score":[3,1],"koef":{"w1":1.74,"w2":3.37,"x":4.43},"date":"11.09.2004"},{"teams":["Portsmouth","Fulham"],"score":[4,3],"koef":{"w1":2.24,"w2":3.16,"x":2.93},"date":"30.08.2004"},{"teams":["Manchester United","Everton"],"score":[0,0],"koef":{"w1":1.31,"w2":4.51,"x":8.73},"date":"30.08.2004"},{"teams":["Bolton","Liverpool"],"score":[1,0],"koef":{"w1":3.05,"w2":3.17,"x":2.17},"date":"29.08.2004"},{"teams":["Aston Villa","Newcastle Utd"],"score":[4,2],"koef":{"w1":2.32,"w2":3.13,"x":2.83},"date":"28.08.2004"},{"teams":["Blackburn","Manchester United"],"score":[1,1],"koef":{"w1":4.11,"w2":3.28,"x":1.8},"date":"28.08.2004"},{"teams":["Chelsea","Southampton"],"score":[2,1],"koef":{"w1":1.27,"w2":4.73,"x":9.45},"date":"28.08.2004"},{"teams":["Everton","West Brom"],"score":[2,1],"koef":{"w1":1.96,"w2":3.17,"x":3.58},"date":"28.08.2004"},{"teams":["Manchester City","Charlton"],"score":[4,0],"koef":{"w1":2.08,"w2":3.18,"x":3.22},"date":"28.08.2004"},{"teams":["Middlesbrough","Crystal Palace"],"score":[2,1],"koef":{"w1":1.52,"w2":3.61,"x":5.95},"date":"28.08.2004"},{"teams":["Norwich","Arsenal"],"score":[1,4],"koef":{"w1":7.64,"w2":4.01,"x":1.38},"date":"28.08.2004"},{"teams":["Tottenham","Birmingham"],"score":[1,0],"koef":{"w1":2.03,"w2":3.18,"x":3.38},"date":"28.08.2004"},{"teams":["Arsenal","Blackburn"],"score":[3,0],"koef":{"w1":1.25,"w2":4.94,"x":9.66},"date":"25.08.2004"},{"teams":["Charlton","Aston Villa"],"score":[3,0],"koef":{"w1":2.38,"w2":3.16,"x":2.72},"date":"25.08.2004"},{"teams":["Fulham","Middlesbrough"],"score":[0,2],"koef":{"w1":2.31,"w2":3.17,"x":2.8},"date":"25.08.2004"},{"teams":["Newcastle Utd","Norwich"],"score":[2,2],"koef":{"w1":1.46,"w2":3.74,"x":6.59},"date":"25.08.2004"},{"teams":["Southampton","Bolton"],"score":[1,2],"koef":{"w1":2.24,"w2":3.18,"x":2.91},"date":"25.08.2004"},{"teams":["West Brom","Tottenham"],"score":[1,1],"koef":{"w1":2.6,"w2":3.14,"x":2.48},"date":"25.08.2004"},{"teams":["Birmingham","Manchester City"],"score":[1,0],"koef":{"w1":1.92,"w2":3.23,"x":3.67},"date":"24.08.2004"},{"teams":["Crystal Palace","Chelsea"],"score":[0,2],"koef":{"w1":7.21,"w2":3.83,"x":1.42},"date":"24.08.2004"},{"teams":["Arsenal","Middlesbrough"],"score":[5,3],"koef":{"w1":1.32,"w2":4.38,"x":8.62},"date":"22.08.2004"},{"teams":["West Brom","Aston Villa"],"score":[1,1],"koef":{"w1":2.78,"w2":3.08,"x":2.38},"date":"22.08.2004"},{"teams":["Birmingham","Chelsea"],"score":[0,1],"koef":{"w1":4.33,"w2":3.28,"x":1.76},"date":"21.08.2004"},{"teams":["Charlton","Portsmouth"],"score":[2,1],"koef":{"w1":1.93,"w2":3.21,"x":3.63},"date":"21.08.2004"},{"teams":["Crystal Palace","Everton"],"score":[1,3],"koef":{"w1":2.26,"w2":3.15,"x":2.88},"date":"21.08.2004"},{"teams":["Fulham","Bolton"],"score":[2,0],"koef":{"w1":2.19,"w2":3.18,"x":2.99},"date":"21.08.2004"},{"teams":["Liverpool","Manchester City"],"score":[2,1],"koef":{"w1":1.54,"w2":3.51,"x":5.84},"date":"21.08.2004"},{"teams":["Manchester United","Norwich"],"score":[2,1],"koef":{"w1":1.27,"w2":4.76,"x":9.07},"date":"21.08.2004"},{"teams":["Newcastle Utd","Tottenham"],"score":[0,1],"koef":{"w1":1.66,"w2":3.37,"x":4.91},"date":"21.08.2004"},{"teams":["Southampton","Blackburn"],"score":[3,2],"koef":{"w1":2.23,"w2":3.17,"x":2.96},"date":"21.08.2004"},{"teams":["Chelsea","Manchester United"],"score":[1,0],"koef":{"w1":2.04,"w2":3.21,"x":3.37},"date":"15.08.2004"},{"teams":["Everton","Arsenal"],"score":[1,4],"koef":{"w1":4.89,"w2":3.34,"x":1.67},"date":"15.08.2004"},{"teams":["Aston Villa","Southampton"],"score":[2,0],"koef":{"w1":1.89,"w2":3.2,"x":3.85},"date":"14.08.2004"},{"teams":["Blackburn","West Brom"],"score":[1,1],"koef":{"w1":1.78,"w2":3.26,"x":4.26},"date":"14.08.2004"},{"teams":["Bolton","Charlton"],"score":[4,1],"koef":{"w1":2.2,"w2":3.18,"x":2.98},"date":"14.08.2004"},{"teams":["Manchester City","Fulham"],"score":[1,1],"koef":{"w1":2.07,"w2":3.19,"x":3.25},"date":"14.08.2004"},{"teams":["Middlesbrough","Newcastle Utd"],"score":[2,2],"koef":{"w1":2.3,"w2":3.18,"x":2.83},"date":"14.08.2004"},{"teams":["Norwich","Crystal Palace"],"score":[1,1],"koef":{"w1":2.04,"w2":3.18,"x":3.34},"date":"14.08.2004"},{"teams":["Portsmouth","Birmingham"],"score":[1,1],"koef":{"w1":2.36,"w2":3.19,"x":2.74},"date":"14.08.2004"},{"teams":["Tottenham","Liverpool"],"score":[1,1],"koef":{"w1":2.93,"w2":3.17,"x":2.23},"date":"14.08.2004"}]