[{"teams":["Aston Villa","Liverpool"],"score":[1,0],"koef":{"w1":3.37,"w2":3.34,"x":2.15},"date":"22.05.2011"},{"teams":["Bolton","Manchester City"],"score":[0,2],"koef":{"w1":4.86,"w2":3.71,"x":1.69},"date":"22.05.2011"},{"teams":["Everton","Chelsea"],"score":[1,0],"koef":{"w1":3.03,"w2":3.31,"x":2.32},"date":"22.05.2011"},{"teams":["Fulham","Arsenal"],"score":[2,2],"koef":{"w1":3.83,"w2":3.53,"x":1.93},"date":"22.05.2011"},{"teams":["Manchester United","Blackpool"],"score":[4,2],"koef":{"w1":1.43,"w2":4.75,"x":6.65},"date":"22.05.2011"},{"teams":["Newcastle Utd","West Brom"],"score":[3,3],"koef":{"w1":2,"w2":3.42,"x":3.69},"date":"22.05.2011"},{"teams":["Stoke City","Wigan"],"score":[0,1],"koef":{"w1":2.14,"w2":3.41,"x":3.3},"date":"22.05.2011"},{"teams":["Tottenham","Birmingham"],"score":[2,1],"koef":{"w1":1.54,"w2":3.98,"x":6.09},"date":"22.05.2011"},{"teams":["West Ham","Sunderland"],"score":[0,3],"koef":{"w1":1.92,"w2":3.54,"x":3.82},"date":"22.05.2011"},{"teams":["Wolves","Blackburn"],"score":[2,3],"koef":{"w1":2.28,"w2":2.96,"x":3.46},"date":"22.05.2011"},{"teams":["Manchester City","Stoke City"],"score":[3,0],"koef":{"w1":1.4,"w2":4.42,"x":8.13},"date":"17.05.2011"},{"teams":["Arsenal","Aston Villa"],"score":[1,2],"koef":{"w1":1.38,"w2":4.66,"x":8.09},"date":"15.05.2011"},{"teams":["Birmingham","Fulham"],"score":[0,2],"koef":{"w1":2.14,"w2":3.26,"x":3.48},"date":"15.05.2011"},{"teams":["Chelsea","Newcastle Utd"],"score":[2,2],"koef":{"w1":1.22,"w2":6.07,"x":13.01},"date":"15.05.2011"},{"teams":["Liverpool","Tottenham"],"score":[0,2],"koef":{"w1":1.64,"w2":3.78,"x":5.43},"date":"15.05.2011"},{"teams":["Wigan","West Ham"],"score":[3,2],"koef":{"w1":1.86,"w2":3.62,"x":4.01},"date":"15.05.2011"},{"teams":["Blackburn","Manchester United"],"score":[1,1],"koef":{"w1":6.25,"w2":3.43,"x":1.65},"date":"14.05.2011"},{"teams":["Blackpool","Bolton"],"score":[4,3],"koef":{"w1":2.03,"w2":3.51,"x":3.51},"date":"14.05.2011"},{"teams":["Sunderland","Wolves"],"score":[1,3],"koef":{"w1":2.9,"w2":3.23,"x":2.46},"date":"14.05.2011"},{"teams":["West Brom","Everton"],"score":[1,0],"koef":{"w1":2.64,"w2":3.26,"x":2.66},"date":"14.05.2011"},{"teams":["Manchester City","Tottenham"],"score":[1,0],"koef":{"w1":1.94,"w2":3.38,"x":4.05},"date":"10.05.2011"},{"teams":["Fulham","Liverpool"],"score":[2,5],"koef":{"w1":2.81,"w2":3.2,"x":2.56},"date":"09.05.2011"},{"teams":["Manchester United","Chelsea"],"score":[2,1],"koef":{"w1":2.29,"w2":3.17,"x":3.27},"date":"08.05.2011"},{"teams":["Stoke City","Arsenal"],"score":[3,1],"koef":{"w1":4.3,"w2":3.37,"x":1.89},"date":"08.05.2011"},{"teams":["Wolves","West Brom"],"score":[3,1],"koef":{"w1":2.25,"w2":3.3,"x":3.18},"date":"08.05.2011"},{"teams":["Aston Villa","Wigan"],"score":[1,1],"koef":{"w1":1.75,"w2":3.57,"x":4.82},"date":"07.05.2011"},{"teams":["Bolton","Sunderland"],"score":[1,2],"koef":{"w1":1.73,"w2":3.51,"x":5.03},"date":"07.05.2011"},{"teams":["Everton","Manchester City"],"score":[2,1],"koef":{"w1":2.54,"w2":3.2,"x":2.84},"date":"07.05.2011"},{"teams":["Newcastle Utd","Birmingham"],"score":[2,1],"koef":{"w1":1.87,"w2":3.4,"x":4.38},"date":"07.05.2011"},{"teams":["Tottenham","Blackpool"],"score":[1,1],"koef":{"w1":1.31,"w2":5.42,"x":9},"date":"07.05.2011"},{"teams":["West Ham","Blackburn"],"score":[1,1],"koef":{"w1":2.05,"w2":3.36,"x":3.62},"date":"07.05.2011"},{"teams":["Arsenal","Manchester United"],"score":[1,0],"koef":{"w1":2.64,"w2":3.22,"x":2.73},"date":"01.05.2011"},{"teams":["Birmingham","Wolves"],"score":[1,1],"koef":{"w1":2.13,"w2":3.28,"x":3.5},"date":"01.05.2011"},{"teams":["Liverpool","Newcastle Utd"],"score":[3,0],"koef":{"w1":1.46,"w2":4.11,"x":7.58},"date":"01.05.2011"},{"teams":["Manchester City","West Ham"],"score":[2,1],"koef":{"w1":1.37,"w2":4.66,"x":8.76},"date":"01.05.2011"},{"teams":["Blackburn","Bolton"],"score":[1,0],"koef":{"w1":1.9,"w2":3.44,"x":4.1},"date":"30.04.2011"},{"teams":["Blackpool","Stoke City"],"score":[0,0],"koef":{"w1":2.62,"w2":3.42,"x":2.59},"date":"30.04.2011"},{"teams":["Chelsea","Tottenham"],"score":[2,1],"koef":{"w1":1.49,"w2":4.15,"x":6.78},"date":"30.04.2011"},{"teams":["Sunderland","Fulham"],"score":[0,3],"koef":{"w1":2.71,"w2":3.14,"x":2.69},"date":"30.04.2011"},{"teams":["West Brom","Aston Villa"],"score":[2,1],"koef":{"w1":2.45,"w2":3.23,"x":2.91},"date":"30.04.2011"},{"teams":["Wigan","Everton"],"score":[1,1],"koef":{"w1":2.99,"w2":3.22,"x":2.41},"date":"30.04.2011"},{"teams":["Fulham","Bolton"],"score":[3,0],"koef":{"w1":1.78,"w2":3.53,"x":4.64},"date":"27.04.2011"},{"teams":["Stoke City","Wolves"],"score":[3,0],"koef":{"w1":1.78,"w2":3.48,"x":4.74},"date":"26.04.2011"},{"teams":["Blackburn","Manchester City"],"score":[0,1],"koef":{"w1":4.04,"w2":3.48,"x":1.91},"date":"25.04.2011"},{"teams":["Bolton","Arsenal"],"score":[2,1],"koef":{"w1":5.35,"w2":3.88,"x":1.63},"date":"24.04.2011"},{"teams":["Aston Villa","Stoke City"],"score":[1,1],"koef":{"w1":2.08,"w2":3.2,"x":3.74},"date":"23.04.2011"},{"teams":["Blackpool","Newcastle Utd"],"score":[1,1],"koef":{"w1":2.82,"w2":3.37,"x":2.44},"date":"23.04.2011"},{"teams":["Chelsea","West Ham"],"score":[3,0],"koef":{"w1":1.2,"w2":6.44,"x":14.17},"date":"23.04.2011"},{"teams":["Liverpool","Birmingham"],"score":[5,0],"koef":{"w1":1.49,"w2":3.99,"x":7.22},"date":"23.04.2011"},{"teams":["Manchester United","Everton"],"score":[1,0],"koef":{"w1":1.5,"w2":3.88,"x":7.24},"date":"23.04.2011"},{"teams":["Sunderland","Wigan"],"score":[4,2],"koef":{"w1":2.11,"w2":3.24,"x":3.61},"date":"23.04.2011"},{"teams":["Tottenham","West Brom"],"score":[2,2],"koef":{"w1":1.53,"w2":4.02,"x":6.31},"date":"23.04.2011"},{"teams":["Wolves","Fulham"],"score":[1,1],"koef":{"w1":2.46,"w2":3.22,"x":2.91},"date":"23.04.2011"},{"teams":["Chelsea","Birmingham"],"score":[3,1],"koef":{"w1":1.2,"w2":6.26,"x":15.64},"date":"20.04.2011"},{"teams":["Tottenham","Arsenal"],"score":[3,3],"koef":{"w1":2.88,"w2":3.29,"x":2.45},"date":"20.04.2011"},{"teams":["Newcastle Utd","Manchester United"],"score":[0,0],"koef":{"w1":5.5,"w2":3.69,"x":1.64},"date":"19.04.2011"},{"teams":["Arsenal","Liverpool"],"score":[1,1],"koef":{"w1":1.72,"w2":3.74,"x":4.82},"date":"17.04.2011"},{"teams":["Birmingham","Sunderland"],"score":[2,0],"koef":{"w1":2.05,"w2":3.27,"x":3.73},"date":"16.04.2011"},{"teams":["Blackpool","Wigan"],"score":[1,3],"koef":{"w1":2.36,"w2":3.37,"x":2.92},"date":"16.04.2011"},{"teams":["Everton","Blackburn"],"score":[2,0],"koef":{"w1":1.7,"w2":3.56,"x":5.23},"date":"16.04.2011"},{"teams":["West Brom","Chelsea"],"score":[1,3],"koef":{"w1":5.16,"w2":3.6,"x":1.7},"date":"16.04.2011"},{"teams":["West Ham","Aston Villa"],"score":[1,2],"koef":{"w1":2.37,"w2":3.29,"x":3},"date":"16.04.2011"},{"teams":["Liverpool","Manchester City"],"score":[3,0],"koef":{"w1":2.54,"w2":3.24,"x":2.82},"date":"11.04.2011"},{"teams":["Aston Villa","Newcastle Utd"],"score":[1,0],"koef":{"w1":1.69,"w2":3.78,"x":4.9},"date":"10.04.2011"},{"teams":["Blackpool","Arsenal"],"score":[1,3],"koef":{"w1":7.03,"w2":4.5,"x":1.44},"date":"10.04.2011"},{"teams":["Blackburn","Birmingham"],"score":[1,1],"koef":{"w1":1.96,"w2":3.32,"x":4},"date":"09.04.2011"},{"teams":["Bolton","West Ham"],"score":[3,0],"koef":{"w1":2.33,"w2":3.23,"x":3.12},"date":"09.04.2011"},{"teams":["Chelsea","Wigan"],"score":[1,0],"koef":{"w1":1.22,"w2":5.93,"x":14.72},"date":"09.04.2011"},{"teams":["Manchester United","Fulham"],"score":[2,0],"koef":{"w1":1.45,"w2":4.19,"x":7.79},"date":"09.04.2011"},{"teams":["Sunderland","West Brom"],"score":[2,3],"koef":{"w1":2.21,"w2":3.27,"x":3.32},"date":"09.04.2011"},{"teams":["Tottenham","Stoke City"],"score":[3,2],"koef":{"w1":1.66,"w2":3.68,"x":5.41},"date":"09.04.2011"},{"teams":["Wolves","Everton"],"score":[0,3],"koef":{"w1":2.45,"w2":3.25,"x":2.91},"date":"09.04.2011"},{"teams":["Fulham","Blackpool"],"score":[3,0],"koef":{"w1":1.48,"w2":4.33,"x":6.58},"date":"03.04.2011"},{"teams":["Manchester City","Sunderland"],"score":[5,0],"koef":{"w1":1.46,"w2":4.17,"x":7.37},"date":"03.04.2011"},{"teams":["Arsenal","Blackburn"],"score":[0,0],"koef":{"w1":1.23,"w2":5.96,"x":12.68},"date":"02.04.2011"},{"teams":["Birmingham","Bolton"],"score":[2,1],"koef":{"w1":2.39,"w2":3.25,"x":2.99},"date":"02.04.2011"},{"teams":["Everton","Aston Villa"],"score":[2,2],"koef":{"w1":2.01,"w2":3.33,"x":3.83},"date":"02.04.2011"},{"teams":["Newcastle Utd","Wolves"],"score":[4,1],"koef":{"w1":2.02,"w2":3.35,"x":3.72},"date":"02.04.2011"},{"teams":["Stoke City","Chelsea"],"score":[1,1],"koef":{"w1":5.47,"w2":3.6,"x":1.67},"date":"02.04.2011"},{"teams":["West Brom","Liverpool"],"score":[2,1],"koef":{"w1":3.22,"w2":3.26,"x":2.26},"date":"02.04.2011"},{"teams":["West Ham","Manchester United"],"score":[2,4],"koef":{"w1":4,"w2":3.35,"x":1.96},"date":"02.04.2011"},{"teams":["Wigan","Tottenham"],"score":[0,0],"koef":{"w1":3.14,"w2":3.27,"x":2.29},"date":"02.04.2011"},{"teams":["Chelsea","Manchester City"],"score":[2,0],"koef":{"w1":1.64,"w2":3.75,"x":5.5},"date":"20.03.2011"},{"teams":["Sunderland","Liverpool"],"score":[0,2],"koef":{"w1":2.77,"w2":3.21,"x":2.59},"date":"20.03.2011"},{"teams":["Aston Villa","Wolves"],"score":[0,1],"koef":{"w1":1.94,"w2":3.37,"x":4.06},"date":"19.03.2011"},{"teams":["Blackburn","Blackpool"],"score":[2,2],"koef":{"w1":1.75,"w2":3.71,"x":4.55},"date":"19.03.2011"},{"teams":["Everton","Fulham"],"score":[2,1],"koef":{"w1":1.98,"w2":3.28,"x":3.97},"date":"19.03.2011"},{"teams":["Manchester United","Bolton"],"score":[1,0],"koef":{"w1":1.39,"w2":4.43,"x":8.61},"date":"19.03.2011"},{"teams":["Stoke City","Newcastle Utd"],"score":[4,0],"koef":{"w1":2.16,"w2":3.22,"x":3.49},"date":"19.03.2011"},{"teams":["Tottenham","West Ham"],"score":[0,0],"koef":{"w1":1.64,"w2":3.73,"x":5.52},"date":"19.03.2011"},{"teams":["West Brom","Arsenal"],"score":[2,2],"koef":{"w1":4.35,"w2":3.48,"x":1.84},"date":"19.03.2011"},{"teams":["Wigan","Birmingham"],"score":[2,1],"koef":{"w1":2.18,"w2":3.26,"x":3.39},"date":"19.03.2011"},{"teams":["Everton","Birmingham"],"score":[1,1],"koef":{"w1":1.54,"w2":3.87,"x":6.66},"date":"09.03.2011"},{"teams":["Blackpool","Chelsea"],"score":[1,3],"koef":{"w1":9.86,"w2":5.46,"x":1.29},"date":"07.03.2011"},{"teams":["Liverpool","Manchester United"],"score":[3,1],"koef":{"w1":2.89,"w2":3.21,"x":2.49},"date":"06.03.2011"},{"teams":["Wolves","Tottenham"],"score":[3,3],"koef":{"w1":2.9,"w2":3.25,"x":2.45},"date":"06.03.2011"},{"teams":["Arsenal","Sunderland"],"score":[0,0],"koef":{"w1":1.41,"w2":4.38,"x":8.25},"date":"05.03.2011"},{"teams":["Birmingham","West Brom"],"score":[1,3],"koef":{"w1":2.46,"w2":3.2,"x":2.94},"date":"05.03.2011"},{"teams":["Bolton","Aston Villa"],"score":[3,2],"koef":{"w1":2.12,"w2":3.33,"x":3.44},"date":"05.03.2011"},{"teams":["Fulham","Blackburn"],"score":[3,2],"koef":{"w1":1.63,"w2":3.69,"x":5.64},"date":"05.03.2011"},{"teams":["Manchester City","Wigan"],"score":[1,0],"koef":{"w1":1.35,"w2":4.68,"x":9.62},"date":"05.03.2011"},{"teams":["Newcastle Utd","Everton"],"score":[1,2],"koef":{"w1":2.52,"w2":3.2,"x":2.84},"date":"05.03.2011"},{"teams":["West Ham","Stoke City"],"score":[3,0],"koef":{"w1":2.05,"w2":3.29,"x":3.69},"date":"05.03.2011"},{"teams":["Chelsea","Manchester United"],"score":[2,1],"koef":{"w1":2.14,"w2":3.25,"x":3.54},"date":"01.03.2011"},{"teams":["Stoke City","West Brom"],"score":[1,1],"koef":{"w1":1.85,"w2":3.42,"x":4.41},"date":"28.02.2011"},{"teams":["Manchester City","Fulham"],"score":[1,1],"koef":{"w1":1.63,"w2":3.59,"x":5.91},"date":"27.02.2011"},{"teams":["West Ham","Liverpool"],"score":[3,1],"koef":{"w1":3.45,"w2":3.26,"x":2.15},"date":"27.02.2011"},{"teams":["Aston Villa","Blackburn"],"score":[4,1],"koef":{"w1":1.77,"w2":3.51,"x":4.75},"date":"26.02.2011"},{"teams":["Everton","Sunderland"],"score":[2,0],"koef":{"w1":1.68,"w2":3.62,"x":5.32},"date":"26.02.2011"},{"teams":["Newcastle Utd","Bolton"],"score":[1,1],"koef":{"w1":2,"w2":3.38,"x":3.78},"date":"26.02.2011"},{"teams":["Wigan","Manchester United"],"score":[0,4],"koef":{"w1":6.51,"w2":3.85,"x":1.54},"date":"26.02.2011"},{"teams":["Wolves","Blackpool"],"score":[4,0],"koef":{"w1":1.7,"w2":3.78,"x":4.74},"date":"26.02.2011"},{"teams":["Arsenal","Stoke City"],"score":[1,0],"koef":{"w1":1.32,"w2":4.97,"x":10.26},"date":"23.02.2011"},{"teams":["Blackpool","Tottenham"],"score":[3,1],"koef":{"w1":4.27,"w2":3.69,"x":1.8},"date":"22.02.2011"},{"teams":["West Brom","Wolves"],"score":[1,1],"koef":{"w1":2.04,"w2":3.27,"x":3.79},"date":"20.02.2011"},{"teams":["Birmingham","Newcastle Utd"],"score":[0,2],"koef":{"w1":2.46,"w2":3.19,"x":2.94},"date":"15.02.2011"},{"teams":["Fulham","Chelsea"],"score":[0,0],"koef":{"w1":5.03,"w2":3.52,"x":1.73},"date":"14.02.2011"},{"teams":["Bolton","Everton"],"score":[2,0],"koef":{"w1":2.78,"w2":3.26,"x":2.53},"date":"13.02.2011"},{"teams":["Arsenal","Wolves"],"score":[2,0],"koef":{"w1":1.25,"w2":5.7,"x":12.11},"date":"12.02.2011"},{"teams":["Birmingham","Stoke City"],"score":[1,0],"koef":{"w1":2.48,"w2":3.16,"x":2.93},"date":"12.02.2011"},{"teams":["Blackburn","Newcastle Utd"],"score":[0,0],"koef":{"w1":2.22,"w2":3.23,"x":3.31},"date":"12.02.2011"},{"teams":["Blackpool","Aston Villa"],"score":[1,1],"koef":{"w1":3.21,"w2":3.48,"x":2.17},"date":"12.02.2011"},{"teams":["Liverpool","Wigan"],"score":[1,1],"koef":{"w1":1.38,"w2":4.45,"x":8.65},"date":"12.02.2011"},{"teams":["Manchester United","Manchester City"],"score":[2,1],"koef":{"w1":1.89,"w2":3.38,"x":4.3},"date":"12.02.2011"},{"teams":["Sunderland","Tottenham"],"score":[1,2],"koef":{"w1":2.53,"w2":3.23,"x":2.81},"date":"12.02.2011"},{"teams":["West Brom","West Ham"],"score":[3,3],"koef":{"w1":1.82,"w2":3.66,"x":4.22},"date":"12.02.2011"},{"teams":["Chelsea","Liverpool"],"score":[0,1],"koef":{"w1":1.51,"w2":4.21,"x":6.3},"date":"06.02.2011"},{"teams":["West Ham","Birmingham"],"score":[0,1],"koef":{"w1":1.96,"w2":3.35,"x":3.96},"date":"06.02.2011"},{"teams":["Aston Villa","Fulham"],"score":[2,2],"koef":{"w1":2.02,"w2":3.25,"x":3.86},"date":"05.02.2011"},{"teams":["Everton","Blackpool"],"score":[5,3],"koef":{"w1":1.43,"w2":4.43,"x":7.46},"date":"05.02.2011"},{"teams":["Manchester City","West Brom"],"score":[3,0],"koef":{"w1":1.42,"w2":4.33,"x":7.98},"date":"05.02.2011"},{"teams":["Newcastle Utd","Arsenal"],"score":[4,4],"koef":{"w1":4.87,"w2":3.56,"x":1.74},"date":"05.02.2011"},{"teams":["Stoke City","Sunderland"],"score":[3,2],"koef":{"w1":2,"w2":3.28,"x":3.92},"date":"05.02.2011"},{"teams":["Tottenham","Bolton"],"score":[2,1],"koef":{"w1":1.59,"w2":3.74,"x":6.04},"date":"05.02.2011"},{"teams":["Wigan","Blackburn"],"score":[4,3],"koef":{"w1":2.49,"w2":3.24,"x":2.84},"date":"05.02.2011"},{"teams":["Wolves","Manchester United"],"score":[2,1],"koef":{"w1":7.54,"w2":4.19,"x":1.45},"date":"05.02.2011"},{"teams":["Birmingham","Manchester City"],"score":[2,2],"koef":{"w1":4.62,"w2":3.5,"x":1.79},"date":"02.02.2011"},{"teams":["Blackburn","Tottenham"],"score":[0,1],"koef":{"w1":2.92,"w2":3.23,"x":2.44},"date":"02.02.2011"},{"teams":["Blackpool","West Ham"],"score":[1,3],"koef":{"w1":2.25,"w2":3.41,"x":3.07},"date":"02.02.2011"},{"teams":["Bolton","Wolves"],"score":[1,0],"koef":{"w1":1.85,"w2":3.42,"x":4.35},"date":"02.02.2011"},{"teams":["Fulham","Newcastle Utd"],"score":[1,0],"koef":{"w1":1.87,"w2":3.4,"x":4.3},"date":"02.02.2011"},{"teams":["Liverpool","Stoke City"],"score":[2,0],"koef":{"w1":1.64,"w2":3.55,"x":5.82},"date":"02.02.2011"},{"teams":["Arsenal","Everton"],"score":[2,1],"koef":{"w1":1.45,"w2":4.24,"x":7.43},"date":"01.02.2011"},{"teams":["Manchester United","Aston Villa"],"score":[3,1],"koef":{"w1":1.32,"w2":5.12,"x":9.21},"date":"01.02.2011"},{"teams":["Sunderland","Chelsea"],"score":[2,4],"koef":{"w1":5.03,"w2":3.49,"x":1.73},"date":"01.02.2011"},{"teams":["West Brom","Wigan"],"score":[2,2],"koef":{"w1":1.73,"w2":3.58,"x":4.9},"date":"01.02.2011"},{"teams":["Liverpool","Fulham"],"score":[1,0],"koef":{"w1":1.55,"w2":3.8,"x":6.44},"date":"26.01.2011"},{"teams":["Wigan","Aston Villa"],"score":[1,2],"koef":{"w1":3.1,"w2":3.31,"x":2.29},"date":"25.01.2011"},{"teams":["Blackpool","Manchester United"],"score":[2,3],"koef":{"w1":8.76,"w2":4.9,"x":1.35},"date":"25.01.2011"},{"teams":["Bolton","Chelsea"],"score":[0,4],"koef":{"w1":4.78,"w2":3.51,"x":1.76},"date":"24.01.2011"},{"teams":["Blackburn","West Brom"],"score":[2,0],"koef":{"w1":2.27,"w2":3.29,"x":3.16},"date":"23.01.2011"},{"teams":["Arsenal","Wigan"],"score":[3,0],"koef":{"w1":1.19,"w2":6.54,"x":15.13},"date":"22.01.2011"},{"teams":["Aston Villa","Manchester City"],"score":[1,0],"koef":{"w1":3.41,"w2":3.18,"x":2.22},"date":"22.01.2011"},{"teams":["Blackpool","Sunderland"],"score":[1,2],"koef":{"w1":2.45,"w2":3.28,"x":2.87},"date":"22.01.2011"},{"teams":["Everton","West Ham"],"score":[2,2],"koef":{"w1":1.5,"w2":4.01,"x":7},"date":"22.01.2011"},{"teams":["Fulham","Stoke City"],"score":[2,0],"koef":{"w1":2.15,"w2":3.21,"x":3.52},"date":"22.01.2011"},{"teams":["Manchester United","Birmingham"],"score":[5,0],"koef":{"w1":1.2,"w2":6.32,"x":14.77},"date":"22.01.2011"},{"teams":["Newcastle Utd","Tottenham"],"score":[1,1],"koef":{"w1":3.08,"w2":3.29,"x":2.32},"date":"22.01.2011"},{"teams":["Wolves","Liverpool"],"score":[0,3],"koef":{"w1":2.91,"w2":3.17,"x":2.5},"date":"22.01.2011"},{"teams":["Birmingham","Aston Villa"],"score":[1,1],"koef":{"w1":2.67,"w2":3.09,"x":2.76},"date":"16.01.2011"},{"teams":["Liverpool","Everton"],"score":[2,2],"koef":{"w1":2.36,"w2":3.07,"x":3.23},"date":"16.01.2011"},{"teams":["Sunderland","Newcastle Utd"],"score":[1,1],"koef":{"w1":2.08,"w2":3.21,"x":3.75},"date":"16.01.2011"},{"teams":["Tottenham","Manchester United"],"score":[0,0],"koef":{"w1":2.99,"w2":3.22,"x":2.4},"date":"16.01.2011"},{"teams":["Chelsea","Blackburn"],"score":[2,0],"koef":{"w1":1.25,"w2":5.63,"x":12.14},"date":"15.01.2011"},{"teams":["Manchester City","Wolves"],"score":[4,3],"koef":{"w1":1.37,"w2":4.49,"x":9.46},"date":"15.01.2011"},{"teams":["Stoke City","Bolton"],"score":[2,0],"koef":{"w1":2.13,"w2":3.25,"x":3.52},"date":"15.01.2011"},{"teams":["West Brom","Blackpool"],"score":[3,2],"koef":{"w1":1.76,"w2":3.75,"x":4.41},"date":"15.01.2011"},{"teams":["West Ham","Arsenal"],"score":[0,3],"koef":{"w1":7.24,"w2":4.32,"x":1.45},"date":"15.01.2011"},{"teams":["Wigan","Fulham"],"score":[1,1],"koef":{"w1":2.59,"w2":3.15,"x":2.79},"date":"15.01.2011"},{"teams":["Blackpool","Liverpool"],"score":[2,1],"koef":{"w1":3.76,"w2":3.52,"x":1.95},"date":"12.01.2011"},{"teams":["Arsenal","Manchester City"],"score":[0,0],"koef":{"w1":1.76,"w2":3.63,"x":4.58},"date":"05.01.2011"},{"teams":["Aston Villa","Sunderland"],"score":[0,1],"koef":{"w1":1.91,"w2":3.46,"x":3.98},"date":"05.01.2011"},{"teams":["Blackburn","Liverpool"],"score":[3,1],"koef":{"w1":4.09,"w2":3.46,"x":1.89},"date":"05.01.2011"},{"teams":["Bolton","Wigan"],"score":[1,1],"koef":{"w1":1.73,"w2":3.48,"x":5.02},"date":"05.01.2011"},{"teams":["Everton","Tottenham"],"score":[2,1],"koef":{"w1":2.45,"w2":3.24,"x":2.89},"date":"05.01.2011"},{"teams":["Newcastle Utd","West Ham"],"score":[5,0],"koef":{"w1":1.89,"w2":3.43,"x":4.17},"date":"05.01.2011"},{"teams":["Wolves","Chelsea"],"score":[1,0],"koef":{"w1":6.58,"w2":3.87,"x":1.54},"date":"05.01.2011"},{"teams":["Blackpool","Birmingham"],"score":[1,2],"koef":{"w1":2.12,"w2":3.29,"x":3.48},"date":"04.01.2011"},{"teams":["Fulham","West Brom"],"score":[3,0],"koef":{"w1":2.13,"w2":3.27,"x":3.47},"date":"04.01.2011"},{"teams":["Manchester United","Stoke City"],"score":[2,1],"koef":{"w1":1.36,"w2":4.54,"x":9.39},"date":"04.01.2011"},{"teams":["Chelsea","Aston Villa"],"score":[3,3],"koef":{"w1":1.26,"w2":5.42,"x":11.81},"date":"02.01.2011"},{"teams":["Wigan","Newcastle Utd"],"score":[0,1],"koef":{"w1":2.56,"w2":3.17,"x":2.81},"date":"02.01.2011"},{"teams":["Birmingham","Arsenal"],"score":[0,3],"koef":{"w1":5.9,"w2":3.78,"x":1.59},"date":"01.01.2011"},{"teams":["Liverpool","Bolton"],"score":[2,1],"koef":{"w1":1.68,"w2":3.61,"x":5.24},"date":"01.01.2011"},{"teams":["Manchester City","Blackpool"],"score":[1,0],"koef":{"w1":1.27,"w2":5.55,"x":10.92},"date":"01.01.2011"},{"teams":["Stoke City","Everton"],"score":[2,0],"koef":{"w1":2.87,"w2":3.19,"x":2.5},"date":"01.01.2011"},{"teams":["Sunderland","Blackburn"],"score":[3,0],"koef":{"w1":1.82,"w2":3.44,"x":4.55},"date":"01.01.2011"},{"teams":["Tottenham","Fulham"],"score":[1,0],"koef":{"w1":1.51,"w2":3.94,"x":6.76},"date":"01.01.2011"},{"teams":["West Brom","Manchester United"],"score":[1,2],"koef":{"w1":5.41,"w2":3.65,"x":1.66},"date":"01.01.2011"},{"teams":["West Ham","Wolves"],"score":[2,0],"koef":{"w1":2.01,"w2":3.31,"x":3.78},"date":"01.01.2011"},{"teams":["Chelsea","Bolton"],"score":[1,0],"koef":{"w1":1.3,"w2":5.23,"x":10.08},"date":"29.12.2010"},{"teams":["Liverpool","Wolves"],"score":[0,1],"koef":{"w1":1.32,"w2":4.91,"x":9.97},"date":"29.12.2010"},{"teams":["Wigan","Arsenal"],"score":[2,2],"koef":{"w1":5.79,"w2":3.69,"x":1.62},"date":"29.12.2010"},{"teams":["Birmingham","Manchester United"],"score":[1,1],"koef":{"w1":7.42,"w2":4.08,"x":1.46},"date":"28.12.2010"},{"teams":["Manchester City","Aston Villa"],"score":[4,0],"koef":{"w1":1.45,"w2":4.1,"x":7.88},"date":"28.12.2010"},{"teams":["Stoke City","Fulham"],"score":[0,2],"koef":{"w1":1.9,"w2":3.31,"x":4.27},"date":"28.12.2010"},{"teams":["Sunderland","Blackpool"],"score":[0,2],"koef":{"w1":1.62,"w2":3.73,"x":5.58},"date":"28.12.2010"},{"teams":["Tottenham","Newcastle Utd"],"score":[2,0],"koef":{"w1":1.5,"w2":4.08,"x":6.65},"date":"28.12.2010"},{"teams":["West Brom","Blackburn"],"score":[1,3],"koef":{"w1":1.74,"w2":3.6,"x":4.81},"date":"28.12.2010"},{"teams":["West Ham","Everton"],"score":[1,1],"koef":{"w1":3.4,"w2":3.27,"x":2.16},"date":"28.12.2010"},{"teams":["Arsenal","Chelsea"],"score":[3,1],"koef":{"w1":2.63,"w2":3.22,"x":2.7},"date":"27.12.2010"},{"teams":["Aston Villa","Tottenham"],"score":[1,2],"koef":{"w1":3.43,"w2":3.31,"x":2.14},"date":"26.12.2010"},{"teams":["Blackburn","Stoke City"],"score":[0,2],"koef":{"w1":2.48,"w2":3.17,"x":2.93},"date":"26.12.2010"},{"teams":["Bolton","West Brom"],"score":[2,0],"koef":{"w1":2.06,"w2":3.31,"x":3.68},"date":"26.12.2010"},{"teams":["Fulham","West Ham"],"score":[1,3],"koef":{"w1":1.94,"w2":3.3,"x":4.18},"date":"26.12.2010"},{"teams":["Manchester United","Sunderland"],"score":[2,0],"koef":{"w1":1.26,"w2":5.47,"x":12.32},"date":"26.12.2010"},{"teams":["Newcastle Utd","Manchester City"],"score":[1,3],"koef":{"w1":3.15,"w2":3.26,"x":2.29},"date":"26.12.2010"},{"teams":["Wolves","Wigan"],"score":[1,2],"koef":{"w1":2.05,"w2":3.24,"x":3.78},"date":"26.12.2010"},{"teams":["Manchester City","Everton"],"score":[1,2],"koef":{"w1":1.72,"w2":3.48,"x":5.2},"date":"20.12.2010"},{"teams":["Blackburn","West Ham"],"score":[1,1],"koef":{"w1":1.75,"w2":3.57,"x":4.79},"date":"18.12.2010"},{"teams":["Sunderland","Bolton"],"score":[1,0],"koef":{"w1":2.1,"w2":3.24,"x":3.61},"date":"18.12.2010"},{"teams":["Manchester United","Arsenal"],"score":[1,0],"koef":{"w1":1.84,"w2":3.53,"x":4.24},"date":"13.12.2010"},{"teams":["Bolton","Blackburn"],"score":[2,1],"koef":{"w1":2.03,"w2":3.31,"x":3.75},"date":"12.12.2010"},{"teams":["Tottenham","Chelsea"],"score":[1,1],"koef":{"w1":3.18,"w2":3.35,"x":2.24},"date":"12.12.2010"},{"teams":["Wolves","Birmingham"],"score":[1,0],"koef":{"w1":2.43,"w2":3.16,"x":2.99},"date":"12.12.2010"},{"teams":["Aston Villa","West Brom"],"score":[2,1],"koef":{"w1":2.33,"w2":3.19,"x":3.13},"date":"11.12.2010"},{"teams":["Everton","Wigan"],"score":[0,0],"koef":{"w1":1.45,"w2":4.13,"x":7.73},"date":"11.12.2010"},{"teams":["Fulham","Sunderland"],"score":[0,0],"koef":{"w1":2.13,"w2":3.21,"x":3.56},"date":"11.12.2010"},{"teams":["Newcastle Utd","Liverpool"],"score":[3,1],"koef":{"w1":3.37,"w2":3.29,"x":2.16},"date":"11.12.2010"},{"teams":["Stoke City","Blackpool"],"score":[0,1],"koef":{"w1":1.6,"w2":3.92,"x":5.54},"date":"11.12.2010"},{"teams":["West Ham","Manchester City"],"score":[1,3],"koef":{"w1":4.06,"w2":3.38,"x":1.92},"date":"11.12.2010"},{"teams":["Liverpool","Aston Villa"],"score":[3,0],"koef":{"w1":1.7,"w2":3.51,"x":5.28},"date":"06.12.2010"},{"teams":["Sunderland","West Ham"],"score":[1,0],"koef":{"w1":1.85,"w2":3.48,"x":4.26},"date":"05.12.2010"},{"teams":["West Brom","Newcastle Utd"],"score":[3,1],"koef":{"w1":2.04,"w2":3.44,"x":3.59},"date":"05.12.2010"},{"teams":["Arsenal","Fulham"],"score":[2,1],"koef":{"w1":1.3,"w2":5.05,"x":10.4},"date":"04.12.2010"},{"teams":["Birmingham","Tottenham"],"score":[1,1],"koef":{"w1":3.57,"w2":3.28,"x":2.09},"date":"04.12.2010"},{"teams":["Blackburn","Wolves"],"score":[3,0],"koef":{"w1":1.75,"w2":3.56,"x":4.73},"date":"04.12.2010"},{"teams":["Chelsea","Everton"],"score":[1,1],"koef":{"w1":1.38,"w2":4.52,"x":8.47},"date":"04.12.2010"},{"teams":["Manchester City","Bolton"],"score":[1,0],"koef":{"w1":1.51,"w2":4,"x":6.71},"date":"04.12.2010"},{"teams":["Wigan","Stoke City"],"score":[2,2],"koef":{"w1":3.04,"w2":3.16,"x":2.4},"date":"04.12.2010"},{"teams":["Newcastle Utd","Chelsea"],"score":[1,1],"koef":{"w1":4.96,"w2":3.7,"x":1.69},"date":"28.11.2010"},{"teams":["Tottenham","Liverpool"],"score":[2,1],"koef":{"w1":2.08,"w2":3.35,"x":3.51},"date":"28.11.2010"},{"teams":["Aston Villa","Arsenal"],"score":[2,4],"koef":{"w1":3.9,"w2":3.35,"x":1.97},"date":"27.11.2010"},{"teams":["Bolton","Blackpool"],"score":[2,2],"koef":{"w1":1.55,"w2":3.99,"x":5.97},"date":"27.11.2010"},{"teams":["Everton","West Brom"],"score":[1,4],"koef":{"w1":1.56,"w2":3.85,"x":6.24},"date":"27.11.2010"},{"teams":["Fulham","Birmingham"],"score":[1,1],"koef":{"w1":1.98,"w2":3.25,"x":3.97},"date":"27.11.2010"},{"teams":["Manchester United","Blackburn"],"score":[7,1],"koef":{"w1":1.27,"w2":5.36,"x":11.43},"date":"27.11.2010"},{"teams":["Stoke City","Manchester City"],"score":[1,1],"koef":{"w1":3.38,"w2":3.27,"x":2.17},"date":"27.11.2010"},{"teams":["West Ham","Wigan"],"score":[3,1],"koef":{"w1":1.94,"w2":3.42,"x":3.95},"date":"27.11.2010"},{"teams":["Wolves","Sunderland"],"score":[3,2],"koef":{"w1":2.63,"w2":3.19,"x":2.72},"date":"27.11.2010"},{"teams":["Sunderland","Everton"],"score":[2,2],"koef":{"w1":2.67,"w2":3.15,"x":2.71},"date":"22.11.2010"},{"teams":["Blackburn","Aston Villa"],"score":[2,0],"koef":{"w1":2.21,"w2":3.26,"x":3.26},"date":"21.11.2010"},{"teams":["Fulham","Manchester City"],"score":[1,4],"koef":{"w1":3.27,"w2":3.22,"x":2.24},"date":"21.11.2010"},{"teams":["Arsenal","Tottenham"],"score":[2,3],"koef":{"w1":1.7,"w2":3.68,"x":4.89},"date":"20.11.2010"},{"teams":["Birmingham","Chelsea"],"score":[1,0],"koef":{"w1":5.69,"w2":3.63,"x":1.64},"date":"20.11.2010"},{"teams":["Blackpool","Wolves"],"score":[2,1],"koef":{"w1":2.38,"w2":3.29,"x":2.96},"date":"20.11.2010"},{"teams":["Bolton","Newcastle Utd"],"score":[5,1],"koef":{"w1":2.12,"w2":3.28,"x":3.45},"date":"20.11.2010"},{"teams":["Liverpool","West Ham"],"score":[3,0],"koef":{"w1":1.51,"w2":3.88,"x":7},"date":"20.11.2010"},{"teams":["Manchester United","Wigan"],"score":[2,0],"koef":{"w1":1.23,"w2":5.62,"x":13.48},"date":"20.11.2010"},{"teams":["West Brom","Stoke City"],"score":[0,3],"koef":{"w1":2.29,"w2":3.18,"x":3.21},"date":"20.11.2010"},{"teams":["Chelsea","Sunderland"],"score":[0,3],"koef":{"w1":1.23,"w2":5.71,"x":13.75},"date":"14.11.2010"},{"teams":["Everton","Arsenal"],"score":[1,2],"koef":{"w1":2.97,"w2":3.28,"x":2.37},"date":"14.11.2010"},{"teams":["Aston Villa","Manchester United"],"score":[2,2],"koef":{"w1":5.11,"w2":3.49,"x":1.73},"date":"13.11.2010"},{"teams":["Manchester City","Birmingham"],"score":[0,0],"koef":{"w1":1.4,"w2":4.37,"x":8.38},"date":"13.11.2010"},{"teams":["Newcastle Utd","Fulham"],"score":[0,0],"koef":{"w1":1.97,"w2":3.32,"x":3.93},"date":"13.11.2010"},{"teams":["Stoke City","Liverpool"],"score":[2,0],"koef":{"w1":3.3,"w2":3.19,"x":2.22},"date":"13.11.2010"},{"teams":["Tottenham","Blackburn"],"score":[4,2],"koef":{"w1":1.6,"w2":3.72,"x":5.95},"date":"13.11.2010"},{"teams":["West Ham","Blackpool"],"score":[0,0],"koef":{"w1":1.85,"w2":3.55,"x":4.16},"date":"13.11.2010"},{"teams":["Wigan","West Brom"],"score":[1,0],"koef":{"w1":2.53,"w2":3.25,"x":2.78},"date":"13.11.2010"},{"teams":["Wolves","Bolton"],"score":[2,3],"koef":{"w1":2.45,"w2":3.22,"x":2.88},"date":"13.11.2010"},{"teams":["Aston Villa","Blackpool"],"score":[3,2],"koef":{"w1":1.45,"w2":4.2,"x":7.36},"date":"10.11.2010"},{"teams":["Chelsea","Fulham"],"score":[1,0],"koef":{"w1":1.23,"w2":5.67,"x":13.18},"date":"10.11.2010"},{"teams":["Everton","Bolton"],"score":[1,1],"koef":{"w1":1.62,"w2":3.7,"x":5.7},"date":"10.11.2010"},{"teams":["Manchester City","Manchester United"],"score":[0,0],"koef":{"w1":2.68,"w2":3.2,"x":2.67},"date":"10.11.2010"},{"teams":["Newcastle Utd","Blackburn"],"score":[1,2],"koef":{"w1":1.79,"w2":3.54,"x":4.49},"date":"10.11.2010"},{"teams":["West Ham","West Brom"],"score":[2,2],"koef":{"w1":2.27,"w2":3.29,"x":3.15},"date":"10.11.2010"},{"teams":["Wigan","Liverpool"],"score":[1,1],"koef":{"w1":4.63,"w2":3.57,"x":1.76},"date":"10.11.2010"},{"teams":["Wolves","Arsenal"],"score":[0,2],"koef":{"w1":6.01,"w2":3.94,"x":1.56},"date":"10.11.2010"},{"teams":["Stoke City","Birmingham"],"score":[3,2],"koef":{"w1":2.03,"w2":3.22,"x":3.85},"date":"09.11.2010"},{"teams":["Tottenham","Sunderland"],"score":[1,1],"koef":{"w1":1.51,"w2":3.94,"x":6.7},"date":"09.11.2010"},{"teams":["Arsenal","Newcastle Utd"],"score":[0,1],"koef":{"w1":1.3,"w2":5.36,"x":9.51},"date":"07.11.2010"},{"teams":["Liverpool","Chelsea"],"score":[2,0],"koef":{"w1":3.26,"w2":3.14,"x":2.29},"date":"07.11.2010"},{"teams":["West Brom","Manchester City"],"score":[0,2],"koef":{"w1":3.19,"w2":3.35,"x":2.22},"date":"07.11.2010"},{"teams":["Birmingham","West Ham"],"score":[2,2],"koef":{"w1":1.99,"w2":3.26,"x":3.9},"date":"06.11.2010"},{"teams":["Blackburn","Wigan"],"score":[2,1],"koef":{"w1":1.73,"w2":3.58,"x":4.88},"date":"06.11.2010"},{"teams":["Blackpool","Everton"],"score":[2,2],"koef":{"w1":4.71,"w2":3.55,"x":1.76},"date":"06.11.2010"},{"teams":["Bolton","Tottenham"],"score":[4,2],"koef":{"w1":3.03,"w2":3.23,"x":2.36},"date":"06.11.2010"},{"teams":["Fulham","Aston Villa"],"score":[1,1],"koef":{"w1":2.07,"w2":3.27,"x":3.66},"date":"06.11.2010"},{"teams":["Manchester United","Wolves"],"score":[2,1],"koef":{"w1":1.23,"w2":5.7,"x":13.56},"date":"06.11.2010"},{"teams":["Sunderland","Stoke City"],"score":[2,0],"koef":{"w1":2.12,"w2":3.16,"x":3.62},"date":"06.11.2010"},{"teams":["Blackpool","West Brom"],"score":[2,1],"koef":{"w1":2.95,"w2":3.34,"x":2.36},"date":"01.11.2010"},{"teams":["Aston Villa","Birmingham"],"score":[0,0],"koef":{"w1":1.9,"w2":3.29,"x":4.3},"date":"31.10.2010"},{"teams":["Bolton","Liverpool"],"score":[0,1],"koef":{"w1":3.29,"w2":3.26,"x":2.21},"date":"31.10.2010"},{"teams":["Newcastle Utd","Sunderland"],"score":[5,1],"koef":{"w1":2.12,"w2":3.21,"x":3.57},"date":"31.10.2010"},{"teams":["Arsenal","West Ham"],"score":[1,0],"koef":{"w1":1.18,"w2":6.62,"x":15.27},"date":"30.10.2010"},{"teams":["Blackburn","Chelsea"],"score":[1,2],"koef":{"w1":7.25,"w2":4.16,"x":1.46},"date":"30.10.2010"},{"teams":["Everton","Stoke City"],"score":[1,0],"koef":{"w1":1.57,"w2":3.68,"x":6.39},"date":"30.10.2010"},{"teams":["Fulham","Wigan"],"score":[2,0],"koef":{"w1":1.81,"w2":3.46,"x":4.54},"date":"30.10.2010"},{"teams":["Manchester United","Tottenham"],"score":[2,0],"koef":{"w1":1.58,"w2":3.92,"x":5.74},"date":"30.10.2010"},{"teams":["Wolves","Manchester City"],"score":[2,1],"koef":{"w1":4.59,"w2":3.43,"x":1.81},"date":"30.10.2010"},{"teams":["Liverpool","Blackburn"],"score":[2,1],"koef":{"w1":1.61,"w2":3.72,"x":5.76},"date":"24.10.2010"},{"teams":["Manchester City","Arsenal"],"score":[0,3],"koef":{"w1":2.4,"w2":3.22,"x":2.97},"date":"24.10.2010"},{"teams":["Stoke City","Manchester United"],"score":[1,2],"koef":{"w1":5.47,"w2":3.69,"x":1.64},"date":"24.10.2010"},{"teams":["Birmingham","Blackpool"],"score":[2,0],"koef":{"w1":1.95,"w2":3.39,"x":3.92},"date":"23.10.2010"},{"teams":["Chelsea","Wolves"],"score":[2,0],"koef":{"w1":1.12,"w2":8.11,"x":22.8},"date":"23.10.2010"},{"teams":["Sunderland","Aston Villa"],"score":[1,0],"koef":{"w1":2.3,"w2":3.25,"x":3.13},"date":"23.10.2010"},{"teams":["Tottenham","Everton"],"score":[1,1],"koef":{"w1":2.07,"w2":3.26,"x":3.66},"date":"23.10.2010"},{"teams":["West Brom","Fulham"],"score":[2,1],"koef":{"w1":2.01,"w2":3.29,"x":3.81},"date":"23.10.2010"},{"teams":["West Ham","Newcastle Utd"],"score":[1,2],"koef":{"w1":2.31,"w2":3.28,"x":3.08},"date":"23.10.2010"},{"teams":["Wigan","Bolton"],"score":[1,1],"koef":{"w1":2.44,"w2":3.21,"x":2.92},"date":"23.10.2010"},{"teams":["Blackburn","Sunderland"],"score":[0,0],"koef":{"w1":2.12,"w2":3.21,"x":3.57},"date":"18.10.2010"},{"teams":["Blackpool","Manchester City"],"score":[2,3],"koef":{"w1":5.9,"w2":3.82,"x":1.58},"date":"17.10.2010"},{"teams":["Everton","Liverpool"],"score":[2,0],"koef":{"w1":2.6,"w2":3.02,"x":2.89},"date":"17.10.2010"},{"teams":["Arsenal","Birmingham"],"score":[2,1],"koef":{"w1":1.29,"w2":5.13,"x":10.93},"date":"16.10.2010"},{"teams":["Aston Villa","Chelsea"],"score":[0,0],"koef":{"w1":4.72,"w2":3.54,"x":1.76},"date":"16.10.2010"},{"teams":["Bolton","Stoke City"],"score":[2,1],"koef":{"w1":2.15,"w2":3.23,"x":3.47},"date":"16.10.2010"},{"teams":["Fulham","Tottenham"],"score":[1,2],"koef":{"w1":2.88,"w2":3.19,"x":2.49},"date":"16.10.2010"},{"teams":["Manchester United","West Brom"],"score":[2,2],"koef":{"w1":1.26,"w2":5.53,"x":11.97},"date":"16.10.2010"},{"teams":["Newcastle Utd","Wigan"],"score":[2,2],"koef":{"w1":1.72,"w2":3.63,"x":4.89},"date":"16.10.2010"},{"teams":["Wolves","West Ham"],"score":[1,1],"koef":{"w1":2.28,"w2":3.23,"x":3.17},"date":"16.10.2010"},{"teams":["Chelsea","Arsenal"],"score":[2,0],"koef":{"w1":1.68,"w2":3.76,"x":4.99},"date":"03.10.2010"},{"teams":["Liverpool","Blackpool"],"score":[1,2],"koef":{"w1":1.3,"w2":5.11,"x":10.31},"date":"03.10.2010"},{"teams":["Manchester City","Newcastle Utd"],"score":[2,1],"koef":{"w1":1.45,"w2":4.21,"x":7.53},"date":"03.10.2010"},{"teams":["Birmingham","Everton"],"score":[0,2],"koef":{"w1":2.97,"w2":3.17,"x":2.44},"date":"02.10.2010"},{"teams":["Stoke City","Blackburn"],"score":[1,0],"koef":{"w1":2.24,"w2":3.23,"x":3.25},"date":"02.10.2010"},{"teams":["Sunderland","Manchester United"],"score":[0,0],"koef":{"w1":4.86,"w2":3.49,"x":1.76},"date":"02.10.2010"},{"teams":["Tottenham","Aston Villa"],"score":[2,1],"koef":{"w1":1.82,"w2":3.52,"x":4.37},"date":"02.10.2010"},{"teams":["West Brom","Bolton"],"score":[1,1],"koef":{"w1":2.06,"w2":3.34,"x":3.59},"date":"02.10.2010"},{"teams":["West Ham","Fulham"],"score":[1,1],"koef":{"w1":2.3,"w2":3.22,"x":3.13},"date":"02.10.2010"},{"teams":["Wigan","Wolves"],"score":[2,0],"koef":{"w1":2.28,"w2":3.21,"x":3.19},"date":"02.10.2010"},{"teams":["Bolton","Manchester United"],"score":[2,2],"koef":{"w1":7.62,"w2":4.23,"x":1.44},"date":"26.09.2010"},{"teams":["Newcastle Utd","Stoke City"],"score":[1,2],"koef":{"w1":1.85,"w2":3.48,"x":4.27},"date":"26.09.2010"},{"teams":["Wolves","Aston Villa"],"score":[1,2],"koef":{"w1":2.68,"w2":3.2,"x":2.64},"date":"26.09.2010"},{"teams":["Arsenal","West Brom"],"score":[2,3],"koef":{"w1":1.25,"w2":5.52,"x":12.13},"date":"25.09.2010"},{"teams":["Birmingham","Wigan"],"score":[0,0],"koef":{"w1":1.85,"w2":3.37,"x":4.46},"date":"25.09.2010"},{"teams":["Blackpool","Blackburn"],"score":[1,2],"koef":{"w1":2.95,"w2":3.25,"x":2.4},"date":"25.09.2010"},{"teams":["Fulham","Everton"],"score":[0,0],"koef":{"w1":2.66,"w2":3.19,"x":2.68},"date":"25.09.2010"},{"teams":["Liverpool","Sunderland"],"score":[2,2],"koef":{"w1":1.43,"w2":4.17,"x":8.19},"date":"25.09.2010"},{"teams":["Manchester City","Chelsea"],"score":[1,0],"koef":{"w1":3.44,"w2":3.19,"x":2.18},"date":"25.09.2010"},{"teams":["West Ham","Tottenham"],"score":[1,0],"koef":{"w1":3.36,"w2":3.3,"x":2.16},"date":"25.09.2010"},{"teams":["Chelsea","Blackpool"],"score":[4,0],"koef":{"w1":1.1,"w2":9.23,"x":23.79},"date":"19.09.2010"},{"teams":["Manchester United","Liverpool"],"score":[3,2],"koef":{"w1":1.7,"w2":3.56,"x":5.23},"date":"19.09.2010"},{"teams":["Wigan","Manchester City"],"score":[0,2],"koef":{"w1":4.99,"w2":3.66,"x":1.7},"date":"19.09.2010"},{"teams":["Aston Villa","Bolton"],"score":[1,1],"koef":{"w1":1.66,"w2":3.7,"x":5.29},"date":"18.09.2010"},{"teams":["Blackburn","Fulham"],"score":[1,1],"koef":{"w1":2.01,"w2":3.25,"x":3.87},"date":"18.09.2010"},{"teams":["Everton","Newcastle Utd"],"score":[0,1],"koef":{"w1":1.62,"w2":3.73,"x":5.66},"date":"18.09.2010"},{"teams":["Stoke City","West Ham"],"score":[1,1],"koef":{"w1":1.88,"w2":3.38,"x":4.26},"date":"18.09.2010"},{"teams":["Sunderland","Arsenal"],"score":[1,1],"koef":{"w1":5.45,"w2":3.62,"x":1.65},"date":"18.09.2010"},{"teams":["Tottenham","Wolves"],"score":[3,1],"koef":{"w1":1.46,"w2":4.13,"x":7.55},"date":"18.09.2010"},{"teams":["West Brom","Birmingham"],"score":[3,1],"koef":{"w1":2.21,"w2":3.24,"x":3.33},"date":"18.09.2010"},{"teams":["Stoke City","Aston Villa"],"score":[2,1],"koef":{"w1":2.48,"w2":3.22,"x":2.87},"date":"13.09.2010"},{"teams":["Birmingham","Liverpool"],"score":[0,0],"koef":{"w1":3.83,"w2":3.22,"x":2.03},"date":"12.09.2010"},{"teams":["Arsenal","Bolton"],"score":[4,1],"koef":{"w1":1.23,"w2":5.77,"x":13.04},"date":"11.09.2010"},{"teams":["Everton","Manchester United"],"score":[3,3],"koef":{"w1":3.96,"w2":3.3,"x":1.98},"date":"11.09.2010"},{"teams":["Fulham","Wolves"],"score":[2,1],"koef":{"w1":1.8,"w2":3.45,"x":4.58},"date":"11.09.2010"},{"teams":["Manchester City","Blackburn"],"score":[1,1],"koef":{"w1":1.46,"w2":4.16,"x":7.3},"date":"11.09.2010"},{"teams":["Newcastle Utd","Blackpool"],"score":[0,2],"koef":{"w1":1.45,"w2":4.36,"x":7.07},"date":"11.09.2010"},{"teams":["West Brom","Tottenham"],"score":[1,1],"koef":{"w1":3.26,"w2":3.28,"x":2.22},"date":"11.09.2010"},{"teams":["West Ham","Chelsea"],"score":[1,3],"koef":{"w1":9.43,"w2":4.87,"x":1.33},"date":"11.09.2010"},{"teams":["Wigan","Sunderland"],"score":[1,1],"koef":{"w1":2.43,"w2":3.24,"x":2.92},"date":"11.09.2010"},{"teams":["Aston Villa","Everton"],"score":[1,0],"koef":{"w1":2.61,"w2":3.23,"x":2.69},"date":"29.08.2010"},{"teams":["Bolton","Birmingham"],"score":[2,2],"koef":{"w1":2.08,"w2":3.28,"x":3.59},"date":"29.08.2010"},{"teams":["Liverpool","West Brom"],"score":[1,0],"koef":{"w1":1.28,"w2":5.25,"x":11.13},"date":"29.08.2010"},{"teams":["Sunderland","Manchester City"],"score":[1,0],"koef":{"w1":4.79,"w2":3.61,"x":1.73},"date":"29.08.2010"},{"teams":["Blackburn","Arsenal"],"score":[1,2],"koef":{"w1":4.93,"w2":3.58,"x":1.72},"date":"28.08.2010"},{"teams":["Blackpool","Fulham"],"score":[2,2],"koef":{"w1":3.03,"w2":3.28,"x":2.33},"date":"28.08.2010"},{"teams":["Chelsea","Stoke City"],"score":[2,0],"koef":{"w1":1.11,"w2":8.32,"x":23.43},"date":"28.08.2010"},{"teams":["Manchester United","West Ham"],"score":[3,0],"koef":{"w1":1.13,"w2":7.52,"x":20.93},"date":"28.08.2010"},{"teams":["Tottenham","Wigan"],"score":[0,1],"koef":{"w1":1.25,"w2":5.61,"x":12.01},"date":"28.08.2010"},{"teams":["Wolves","Newcastle Utd"],"score":[1,1],"koef":{"w1":2.44,"w2":3.25,"x":2.88},"date":"28.08.2010"},{"teams":["Manchester City","Liverpool"],"score":[3,0],"koef":{"w1":2.37,"w2":3.16,"x":3.08},"date":"23.08.2010"},{"teams":["Fulham","Manchester United"],"score":[2,2],"koef":{"w1":6.17,"w2":3.75,"x":1.58},"date":"22.08.2010"},{"teams":["Newcastle Utd","Aston Villa"],"score":[6,0],"koef":{"w1":2.59,"w2":3.25,"x":2.7},"date":"22.08.2010"},{"teams":["Arsenal","Blackpool"],"score":[6,0],"koef":{"w1":1.14,"w2":7.39,"x":17.57},"date":"21.08.2010"},{"teams":["Birmingham","Blackburn"],"score":[2,1],"koef":{"w1":2.29,"w2":3.17,"x":3.23},"date":"21.08.2010"},{"teams":["Everton","Wolves"],"score":[1,1],"koef":{"w1":1.47,"w2":4.03,"x":7.36},"date":"21.08.2010"},{"teams":["Stoke City","Tottenham"],"score":[1,2],"koef":{"w1":3.15,"w2":3.24,"x":2.28},"date":"21.08.2010"},{"teams":["West Brom","Sunderland"],"score":[1,0],"koef":{"w1":2.12,"w2":3.29,"x":3.47},"date":"21.08.2010"},{"teams":["West Ham","Bolton"],"score":[1,3],"koef":{"w1":2.23,"w2":3.25,"x":3.25},"date":"21.08.2010"},{"teams":["Wigan","Chelsea"],"score":[0,6],"koef":{"w1":12.9,"w2":5.68,"x":1.23},"date":"21.08.2010"},{"teams":["Manchester United","Newcastle Utd"],"score":[3,0],"koef":{"w1":1.2,"w2":6.2,"x":14.44},"date":"16.08.2010"},{"teams":["Liverpool","Arsenal"],"score":[1,1],"koef":{"w1":2.24,"w2":3.24,"x":3.26},"date":"15.08.2010"},{"teams":["Aston Villa","West Ham"],"score":[3,0],"koef":{"w1":1.91,"w2":3.34,"x":4.15},"date":"14.08.2010"},{"teams":["Blackburn","Everton"],"score":[1,0],"koef":{"w1":2.92,"w2":3.24,"x":2.43},"date":"14.08.2010"},{"teams":["Bolton","Fulham"],"score":[0,0],"koef":{"w1":2.19,"w2":3.26,"x":3.35},"date":"14.08.2010"},{"teams":["Chelsea","West Brom"],"score":[6,0],"koef":{"w1":1.15,"w2":7.12,"x":18.04},"date":"14.08.2010"},{"teams":["Sunderland","Birmingham"],"score":[2,2],"koef":{"w1":2.11,"w2":3.27,"x":3.54},"date":"14.08.2010"},{"teams":["Tottenham","Manchester City"],"score":[0,0],"koef":{"w1":2.23,"w2":3.28,"x":3.24},"date":"14.08.2010"},{"teams":["Wigan","Blackpool"],"score":[0,4],"koef":{"w1":1.74,"w2":3.57,"x":4.81},"date":"14.08.2010"},{"teams":["Wolves","Stoke City"],"score":[2,1],"koef":{"w1":2.38,"w2":3.19,"x":3.04},"date":"14.08.2010"}]