[{"teams":["Chelsea","Everton"],"score":[2,1],"koef":{"w1":1.72,"w2":3.75,"x":4.83},"date":"19.05.2013"},{"teams":["Liverpool","QPR"],"score":[1,0],"koef":{"w1":1.24,"w2":6.19,"x":11.85},"date":"19.05.2013"},{"teams":["Manchester City","Norwich"],"score":[2,3],"koef":{"w1":1.26,"w2":5.72,"x":11.24},"date":"19.05.2013"},{"teams":["Newcastle Utd","Arsenal"],"score":[0,1],"koef":{"w1":5.9,"w2":4.4,"x":1.52},"date":"19.05.2013"},{"teams":["Southampton","Stoke City"],"score":[1,1],"koef":{"w1":1.67,"w2":3.67,"x":5.38},"date":"19.05.2013"},{"teams":["Swansea","Fulham"],"score":[0,3],"koef":{"w1":1.66,"w2":3.81,"x":5.23},"date":"19.05.2013"},{"teams":["Tottenham","Sunderland"],"score":[1,0],"koef":{"w1":1.24,"w2":5.99,"x":12.55},"date":"19.05.2013"},{"teams":["West Brom","Manchester United"],"score":[5,5],"koef":{"w1":3.79,"w2":3.5,"x":1.97},"date":"19.05.2013"},{"teams":["West Ham","Reading"],"score":[4,2],"koef":{"w1":1.61,"w2":3.93,"x":5.64},"date":"19.05.2013"},{"teams":["Wigan","Aston Villa"],"score":[2,2],"koef":{"w1":2.05,"w2":3.47,"x":3.57},"date":"19.05.2013"},{"teams":["Arsenal","Wigan"],"score":[4,1],"koef":{"w1":1.37,"w2":5.29,"x":7.58},"date":"14.05.2013"},{"teams":["Reading","Manchester City"],"score":[0,2],"koef":{"w1":6.5,"w2":4.52,"x":1.48},"date":"14.05.2013"},{"teams":["Everton","West Ham"],"score":[2,0],"koef":{"w1":1.51,"w2":4.14,"x":6.74},"date":"12.05.2013"},{"teams":["Fulham","Liverpool"],"score":[1,3],"koef":{"w1":3.78,"w2":3.46,"x":2},"date":"12.05.2013"},{"teams":["Manchester United","Swansea"],"score":[2,1],"koef":{"w1":1.33,"w2":5.1,"x":9.35},"date":"12.05.2013"},{"teams":["Norwich","West Brom"],"score":[4,0],"koef":{"w1":2.35,"w2":3.27,"x":3.1},"date":"12.05.2013"},{"teams":["QPR","Newcastle Utd"],"score":[1,2],"koef":{"w1":3.01,"w2":3.39,"x":2.34},"date":"12.05.2013"},{"teams":["Stoke City","Tottenham"],"score":[1,2],"koef":{"w1":4.65,"w2":3.54,"x":1.79},"date":"12.05.2013"},{"teams":["Sunderland","Southampton"],"score":[1,1],"koef":{"w1":3.05,"w2":3.08,"x":2.5},"date":"12.05.2013"},{"teams":["Aston Villa","Chelsea"],"score":[1,2],"koef":{"w1":5.18,"w2":3.96,"x":1.65},"date":"11.05.2013"},{"teams":["Chelsea","Tottenham"],"score":[2,2],"koef":{"w1":1.82,"w2":3.69,"x":4.28},"date":"08.05.2013"},{"teams":["Manchester City","West Brom"],"score":[1,0],"koef":{"w1":1.39,"w2":4.72,"x":8.29},"date":"07.05.2013"},{"teams":["Wigan","Swansea"],"score":[2,3],"koef":{"w1":1.77,"w2":3.67,"x":4.56},"date":"07.05.2013"},{"teams":["Sunderland","Stoke City"],"score":[1,1],"koef":{"w1":2.18,"w2":3.12,"x":3.64},"date":"06.05.2013"},{"teams":["Liverpool","Everton"],"score":[0,0],"koef":{"w1":1.95,"w2":3.49,"x":3.93},"date":"05.05.2013"},{"teams":["Manchester United","Chelsea"],"score":[0,1],"koef":{"w1":2.31,"w2":3.38,"x":3.06},"date":"05.05.2013"},{"teams":["Fulham","Reading"],"score":[2,4],"koef":{"w1":1.69,"w2":3.74,"x":5.15},"date":"04.05.2013"},{"teams":["Norwich","Aston Villa"],"score":[1,2],"koef":{"w1":2.5,"w2":3.2,"x":2.91},"date":"04.05.2013"},{"teams":["QPR","Arsenal"],"score":[0,1],"koef":{"w1":8.34,"w2":4.86,"x":1.37},"date":"04.05.2013"},{"teams":["Swansea","Manchester City"],"score":[0,0],"koef":{"w1":4.82,"w2":3.67,"x":1.75},"date":"04.05.2013"},{"teams":["Tottenham","Southampton"],"score":[1,0],"koef":{"w1":1.5,"w2":4.26,"x":6.5},"date":"04.05.2013"},{"teams":["West Brom","Wigan"],"score":[2,3],"koef":{"w1":2.28,"w2":3.41,"x":3.08},"date":"04.05.2013"},{"teams":["West Ham","Newcastle Utd"],"score":[0,0],"koef":{"w1":2.21,"w2":3.41,"x":3.26},"date":"04.05.2013"},{"teams":["Aston Villa","Sunderland"],"score":[6,1],"koef":{"w1":2.2,"w2":3.28,"x":3.42},"date":"29.04.2013"},{"teams":["Arsenal","Manchester United"],"score":[1,1],"koef":{"w1":2.22,"w2":3.52,"x":3.15},"date":"28.04.2013"},{"teams":["Chelsea","Swansea"],"score":[2,0],"koef":{"w1":1.37,"w2":4.93,"x":8.48},"date":"28.04.2013"},{"teams":["Reading","QPR"],"score":[0,0],"koef":{"w1":2.44,"w2":3.43,"x":2.82},"date":"28.04.2013"},{"teams":["Everton","Fulham"],"score":[1,0],"koef":{"w1":1.49,"w2":4.21,"x":7.05},"date":"27.04.2013"},{"teams":["Manchester City","West Ham"],"score":[2,1],"koef":{"w1":1.24,"w2":6.08,"x":12.67},"date":"27.04.2013"},{"teams":["Newcastle Utd","Liverpool"],"score":[0,6],"koef":{"w1":3.02,"w2":3.37,"x":2.35},"date":"27.04.2013"},{"teams":["Southampton","West Brom"],"score":[0,3],"koef":{"w1":1.74,"w2":3.72,"x":4.77},"date":"27.04.2013"},{"teams":["Stoke City","Norwich"],"score":[1,0],"koef":{"w1":2.1,"w2":3.12,"x":3.89},"date":"27.04.2013"},{"teams":["Wigan","Tottenham"],"score":[2,2],"koef":{"w1":3.3,"w2":3.41,"x":2.19},"date":"27.04.2013"},{"teams":["Manchester United","Aston Villa"],"score":[3,0],"koef":{"w1":1.24,"w2":6.31,"x":11.89},"date":"22.04.2013"},{"teams":["Liverpool","Chelsea"],"score":[2,2],"koef":{"w1":2.13,"w2":3.45,"x":3.41},"date":"21.04.2013"},{"teams":["Tottenham","Manchester City"],"score":[3,1],"koef":{"w1":2.75,"w2":3.25,"x":2.62},"date":"21.04.2013"},{"teams":["Fulham","Arsenal"],"score":[0,1],"koef":{"w1":5.9,"w2":4.11,"x":1.57},"date":"20.04.2013"},{"teams":["Norwich","Reading"],"score":[2,1],"koef":{"w1":1.75,"w2":3.62,"x":4.88},"date":"20.04.2013"},{"teams":["QPR","Stoke City"],"score":[0,2],"koef":{"w1":2.13,"w2":3.23,"x":3.66},"date":"20.04.2013"},{"teams":["Sunderland","Everton"],"score":[1,0],"koef":{"w1":3.29,"w2":3.28,"x":2.25},"date":"20.04.2013"},{"teams":["Swansea","Southampton"],"score":[0,0],"koef":{"w1":2.25,"w2":3.32,"x":3.24},"date":"20.04.2013"},{"teams":["West Brom","Newcastle Utd"],"score":[1,1],"koef":{"w1":2.33,"w2":3.33,"x":3.08},"date":"20.04.2013"},{"teams":["West Ham","Wigan"],"score":[2,0],"koef":{"w1":2.35,"w2":3.32,"x":3.06},"date":"20.04.2013"},{"teams":["Fulham","Chelsea"],"score":[0,3],"koef":{"w1":5.05,"w2":3.75,"x":1.7},"date":"17.04.2013"},{"teams":["Manchester City","Wigan"],"score":[1,0],"koef":{"w1":1.28,"w2":5.66,"x":11.1},"date":"17.04.2013"},{"teams":["West Ham","Manchester United"],"score":[2,2],"koef":{"w1":5.06,"w2":3.65,"x":1.72},"date":"17.04.2013"},{"teams":["Arsenal","Everton"],"score":[0,0],"koef":{"w1":1.69,"w2":3.82,"x":5.08},"date":"16.04.2013"},{"teams":["Newcastle Utd","Sunderland"],"score":[0,3],"koef":{"w1":1.84,"w2":3.44,"x":4.55},"date":"14.04.2013"},{"teams":["Stoke City","Manchester United"],"score":[0,2],"koef":{"w1":6.36,"w2":3.81,"x":1.57},"date":"14.04.2013"},{"teams":["Arsenal","Norwich"],"score":[3,1],"koef":{"w1":1.25,"w2":5.98,"x":12.15},"date":"13.04.2013"},{"teams":["Aston Villa","Fulham"],"score":[1,1],"koef":{"w1":2.23,"w2":3.3,"x":3.29},"date":"13.04.2013"},{"teams":["Everton","QPR"],"score":[2,0],"koef":{"w1":1.46,"w2":4.35,"x":7.26},"date":"13.04.2013"},{"teams":["Reading","Liverpool"],"score":[0,0],"koef":{"w1":7.21,"w2":4.54,"x":1.44},"date":"13.04.2013"},{"teams":["Southampton","West Ham"],"score":[1,1],"koef":{"w1":1.77,"w2":3.67,"x":4.65},"date":"13.04.2013"},{"teams":["Manchester United","Manchester City"],"score":[1,2],"koef":{"w1":2.4,"w2":3.27,"x":3.03},"date":"08.04.2013"},{"teams":["Chelsea","Sunderland"],"score":[2,1],"koef":{"w1":1.27,"w2":5.56,"x":11.17},"date":"07.04.2013"},{"teams":["Liverpool","West Ham"],"score":[0,0],"koef":{"w1":1.3,"w2":5.47,"x":9.9},"date":"07.04.2013"},{"teams":["Newcastle Utd","Fulham"],"score":[1,0],"koef":{"w1":1.89,"w2":3.53,"x":4.13},"date":"07.04.2013"},{"teams":["QPR","Wigan"],"score":[1,1],"koef":{"w1":2.35,"w2":3.35,"x":3.01},"date":"07.04.2013"},{"teams":["Tottenham","Everton"],"score":[2,2],"koef":{"w1":2.17,"w2":3.26,"x":3.5},"date":"07.04.2013"},{"teams":["Norwich","Swansea"],"score":[2,2],"koef":{"w1":2.52,"w2":3.23,"x":2.87},"date":"06.04.2013"},{"teams":["Reading","Southampton"],"score":[0,2],"koef":{"w1":3.41,"w2":3.45,"x":2.13},"date":"06.04.2013"},{"teams":["Stoke City","Aston Villa"],"score":[1,3],"koef":{"w1":2.12,"w2":3.22,"x":3.7},"date":"06.04.2013"},{"teams":["West Brom","Arsenal"],"score":[1,2],"koef":{"w1":4.45,"w2":3.69,"x":1.78},"date":"06.04.2013"},{"teams":["Fulham","QPR"],"score":[3,2],"koef":{"w1":2.04,"w2":3.43,"x":3.66},"date":"01.04.2013"},{"teams":["Aston Villa","Liverpool"],"score":[1,2],"koef":{"w1":5.17,"w2":4,"x":1.64},"date":"31.03.2013"},{"teams":["Arsenal","Reading"],"score":[4,1],"koef":{"w1":1.24,"w2":6.12,"x":12.13},"date":"30.03.2013"},{"teams":["Everton","Stoke City"],"score":[1,0],"koef":{"w1":1.7,"w2":3.51,"x":5.57},"date":"30.03.2013"},{"teams":["Manchester City","Newcastle Utd"],"score":[4,0],"koef":{"w1":1.29,"w2":5.42,"x":10.68},"date":"30.03.2013"},{"teams":["Southampton","Chelsea"],"score":[2,1],"koef":{"w1":3.07,"w2":3.32,"x":2.34},"date":"30.03.2013"},{"teams":["Sunderland","Manchester United"],"score":[0,1],"koef":{"w1":5.6,"w2":3.7,"x":1.65},"date":"30.03.2013"},{"teams":["Swansea","Tottenham"],"score":[1,2],"koef":{"w1":3.08,"w2":3.33,"x":2.34},"date":"30.03.2013"},{"teams":["West Ham","West Brom"],"score":[3,1],"koef":{"w1":2.14,"w2":3.34,"x":3.5},"date":"30.03.2013"},{"teams":["Wigan","Norwich"],"score":[1,0],"koef":{"w1":1.81,"w2":3.53,"x":4.61},"date":"30.03.2013"},{"teams":["Chelsea","West Ham"],"score":[2,0],"koef":{"w1":1.36,"w2":4.97,"x":8.43},"date":"17.03.2013"},{"teams":["Sunderland","Norwich"],"score":[1,1],"koef":{"w1":1.99,"w2":3.37,"x":3.89},"date":"17.03.2013"},{"teams":["Tottenham","Fulham"],"score":[0,1],"koef":{"w1":1.51,"w2":4.17,"x":6.68},"date":"17.03.2013"},{"teams":["Wigan","Newcastle Utd"],"score":[2,1],"koef":{"w1":2.23,"w2":3.33,"x":3.27},"date":"17.03.2013"},{"teams":["Aston Villa","QPR"],"score":[3,2],"koef":{"w1":2.34,"w2":3.26,"x":3.13},"date":"16.03.2013"},{"teams":["Everton","Manchester City"],"score":[2,0],"koef":{"w1":3.43,"w2":3.36,"x":2.16},"date":"16.03.2013"},{"teams":["Manchester United","Reading"],"score":[1,0],"koef":{"w1":1.13,"w2":8.34,"x":17.62},"date":"16.03.2013"},{"teams":["Southampton","Liverpool"],"score":[3,1],"koef":{"w1":3.83,"w2":3.61,"x":1.94},"date":"16.03.2013"},{"teams":["Stoke City","West Brom"],"score":[0,0],"koef":{"w1":2.67,"w2":3.13,"x":2.8},"date":"16.03.2013"},{"teams":["Swansea","Arsenal"],"score":[0,2],"koef":{"w1":3.32,"w2":3.41,"x":2.18},"date":"16.03.2013"},{"teams":["Liverpool","Tottenham"],"score":[3,2],"koef":{"w1":1.87,"w2":3.77,"x":3.9},"date":"10.03.2013"},{"teams":["Newcastle Utd","Stoke City"],"score":[2,1],"koef":{"w1":1.77,"w2":3.49,"x":4.91},"date":"10.03.2013"},{"teams":["Norwich","Southampton"],"score":[0,0],"koef":{"w1":2.61,"w2":3.23,"x":2.76},"date":"09.03.2013"},{"teams":["QPR","Sunderland"],"score":[3,1],"koef":{"w1":2.25,"w2":3.25,"x":3.31},"date":"09.03.2013"},{"teams":["Reading","Aston Villa"],"score":[1,2],"koef":{"w1":2.49,"w2":3.29,"x":2.86},"date":"09.03.2013"},{"teams":["West Brom","Swansea"],"score":[2,1],"koef":{"w1":2.27,"w2":3.32,"x":3.19},"date":"09.03.2013"},{"teams":["Aston Villa","Manchester City"],"score":[0,1],"koef":{"w1":7.3,"w2":4.58,"x":1.43},"date":"04.03.2013"},{"teams":["Tottenham","Arsenal"],"score":[2,1],"koef":{"w1":2.34,"w2":3.4,"x":3.01},"date":"03.03.2013"},{"teams":["Chelsea","West Brom"],"score":[1,0],"koef":{"w1":1.39,"w2":4.76,"x":8.25},"date":"02.03.2013"},{"teams":["Everton","Reading"],"score":[3,1],"koef":{"w1":1.37,"w2":4.83,"x":8.78},"date":"02.03.2013"},{"teams":["Manchester United","Norwich"],"score":[4,0],"koef":{"w1":1.27,"w2":5.64,"x":11.22},"date":"02.03.2013"},{"teams":["Southampton","QPR"],"score":[1,2],"koef":{"w1":1.69,"w2":3.8,"x":5.08},"date":"02.03.2013"},{"teams":["Stoke City","West Ham"],"score":[0,1],"koef":{"w1":2.37,"w2":3.19,"x":3.15},"date":"02.03.2013"},{"teams":["Sunderland","Fulham"],"score":[2,2],"koef":{"w1":2.27,"w2":3.26,"x":3.27},"date":"02.03.2013"},{"teams":["Swansea","Newcastle Utd"],"score":[1,0],"koef":{"w1":2.05,"w2":3.45,"x":3.61},"date":"02.03.2013"},{"teams":["Wigan","Liverpool"],"score":[0,4],"koef":{"w1":4.49,"w2":3.71,"x":1.78},"date":"02.03.2013"},{"teams":["West Ham","Tottenham"],"score":[2,3],"koef":{"w1":3.46,"w2":3.31,"x":2.16},"date":"25.02.2013"},{"teams":["Manchester City","Chelsea"],"score":[2,0],"koef":{"w1":2.03,"w2":3.46,"x":3.67},"date":"24.02.2013"},{"teams":["Newcastle Utd","Southampton"],"score":[4,2],"koef":{"w1":2.17,"w2":3.35,"x":3.42},"date":"24.02.2013"},{"teams":["Arsenal","Aston Villa"],"score":[2,1],"koef":{"w1":1.31,"w2":5.41,"x":9.58},"date":"23.02.2013"},{"teams":["Fulham","Stoke City"],"score":[1,0],"koef":{"w1":2.11,"w2":3.24,"x":3.71},"date":"23.02.2013"},{"teams":["Norwich","Everton"],"score":[2,1],"koef":{"w1":3.44,"w2":3.27,"x":2.18},"date":"23.02.2013"},{"teams":["QPR","Manchester United"],"score":[0,2],"koef":{"w1":6.3,"w2":4.18,"x":1.53},"date":"23.02.2013"},{"teams":["Reading","Wigan"],"score":[0,3],"koef":{"w1":2.52,"w2":3.29,"x":2.8},"date":"23.02.2013"},{"teams":["West Brom","Sunderland"],"score":[2,1],"koef":{"w1":1.85,"w2":3.51,"x":4.36},"date":"23.02.2013"},{"teams":["Liverpool","Swansea"],"score":[5,0],"koef":{"w1":1.41,"w2":4.67,"x":7.75},"date":"17.02.2013"},{"teams":["Liverpool","West Brom"],"score":[0,2],"koef":{"w1":1.39,"w2":4.76,"x":8.35},"date":"11.02.2013"},{"teams":["Aston Villa","West Ham"],"score":[2,1],"koef":{"w1":2.78,"w2":3.25,"x":2.58},"date":"10.02.2013"},{"teams":["Manchester United","Everton"],"score":[2,0],"koef":{"w1":1.73,"w2":3.7,"x":4.89},"date":"10.02.2013"},{"teams":["Chelsea","Wigan"],"score":[4,1],"koef":{"w1":1.34,"w2":5.19,"x":8.91},"date":"09.02.2013"},{"teams":["Norwich","Fulham"],"score":[0,0],"koef":{"w1":2.31,"w2":3.3,"x":3.17},"date":"09.02.2013"},{"teams":["Southampton","Manchester City"],"score":[3,1],"koef":{"w1":5.37,"w2":3.93,"x":1.64},"date":"09.02.2013"},{"teams":["Stoke City","Reading"],"score":[2,1],"koef":{"w1":1.87,"w2":3.43,"x":4.42},"date":"09.02.2013"},{"teams":["Sunderland","Arsenal"],"score":[0,1],"koef":{"w1":4.24,"w2":3.54,"x":1.87},"date":"09.02.2013"},{"teams":["Swansea","QPR"],"score":[4,1],"koef":{"w1":1.74,"w2":3.59,"x":4.97},"date":"09.02.2013"},{"teams":["Tottenham","Newcastle Utd"],"score":[2,1],"koef":{"w1":1.65,"w2":3.83,"x":5.44},"date":"09.02.2013"},{"teams":["Manchester City","Liverpool"],"score":[2,2],"koef":{"w1":1.83,"w2":3.6,"x":4.39},"date":"03.02.2013"},{"teams":["West Brom","Tottenham"],"score":[0,1],"koef":{"w1":3.48,"w2":3.33,"x":2.15},"date":"03.02.2013"},{"teams":["Arsenal","Stoke City"],"score":[1,0],"koef":{"w1":1.39,"w2":4.53,"x":8.81},"date":"02.02.2013"},{"teams":["Everton","Aston Villa"],"score":[3,3],"koef":{"w1":1.38,"w2":4.62,"x":8.81},"date":"02.02.2013"},{"teams":["Fulham","Manchester United"],"score":[0,1],"koef":{"w1":6.06,"w2":4.19,"x":1.54},"date":"02.02.2013"},{"teams":["Newcastle Utd","Chelsea"],"score":[3,2],"koef":{"w1":4.02,"w2":3.44,"x":1.94},"date":"02.02.2013"},{"teams":["QPR","Norwich"],"score":[0,0],"koef":{"w1":2.23,"w2":3.22,"x":3.42},"date":"02.02.2013"},{"teams":["Reading","Sunderland"],"score":[2,1],"koef":{"w1":2.42,"w2":3.25,"x":2.98},"date":"02.02.2013"},{"teams":["West Ham","Swansea"],"score":[1,0],"koef":{"w1":2.4,"w2":3.28,"x":3.01},"date":"02.02.2013"},{"teams":["Wigan","Southampton"],"score":[2,2],"koef":{"w1":2.21,"w2":3.34,"x":3.32},"date":"02.02.2013"},{"teams":["Arsenal","Liverpool"],"score":[2,2],"koef":{"w1":2.14,"w2":3.39,"x":3.43},"date":"30.01.2013"},{"teams":["Everton","West Brom"],"score":[2,1],"koef":{"w1":1.57,"w2":4.01,"x":6.08},"date":"30.01.2013"},{"teams":["Fulham","West Ham"],"score":[3,1],"koef":{"w1":2.37,"w2":3.27,"x":3.07},"date":"30.01.2013"},{"teams":["Manchester United","Southampton"],"score":[2,1],"koef":{"w1":1.23,"w2":6.5,"x":11.8},"date":"30.01.2013"},{"teams":["Norwich","Tottenham"],"score":[1,1],"koef":{"w1":4.34,"w2":3.57,"x":1.85},"date":"30.01.2013"},{"teams":["Reading","Chelsea"],"score":[2,2],"koef":{"w1":6.02,"w2":4.12,"x":1.55},"date":"30.01.2013"},{"teams":["Aston Villa","Newcastle Utd"],"score":[1,2],"koef":{"w1":2.75,"w2":3.25,"x":2.61},"date":"29.01.2013"},{"teams":["QPR","Manchester City"],"score":[0,0],"koef":{"w1":7.36,"w2":4.43,"x":1.44},"date":"29.01.2013"},{"teams":["Stoke City","Wigan"],"score":[2,2],"koef":{"w1":2.19,"w2":3.2,"x":3.51},"date":"29.01.2013"},{"teams":["Sunderland","Swansea"],"score":[0,0],"koef":{"w1":2.5,"w2":3.22,"x":2.91},"date":"29.01.2013"},{"teams":["Arsenal","West Ham"],"score":[5,1],"koef":{"w1":1.46,"w2":4.39,"x":7.18},"date":"23.01.2013"},{"teams":["Southampton","Everton"],"score":[0,0],"koef":{"w1":3.67,"w2":3.35,"x":2.06},"date":"21.01.2013"},{"teams":["Chelsea","Arsenal"],"score":[2,1],"koef":{"w1":1.95,"w2":3.55,"x":3.83},"date":"20.01.2013"},{"teams":["Tottenham","Manchester United"],"score":[1,1],"koef":{"w1":2.93,"w2":3.42,"x":2.38},"date":"20.01.2013"},{"teams":["Liverpool","Norwich"],"score":[5,0],"koef":{"w1":1.32,"w2":5.22,"x":9.57},"date":"19.01.2013"},{"teams":["Manchester City","Fulham"],"score":[2,0],"koef":{"w1":1.24,"w2":6.06,"x":12.54},"date":"19.01.2013"},{"teams":["Newcastle Utd","Reading"],"score":[1,2],"koef":{"w1":1.66,"w2":3.81,"x":5.31},"date":"19.01.2013"},{"teams":["Swansea","Stoke City"],"score":[3,1],"koef":{"w1":2.14,"w2":3.22,"x":3.6},"date":"19.01.2013"},{"teams":["West Brom","Aston Villa"],"score":[2,2],"koef":{"w1":1.84,"w2":3.55,"x":4.39},"date":"19.01.2013"},{"teams":["West Ham","QPR"],"score":[1,1],"koef":{"w1":2.06,"w2":3.37,"x":3.66},"date":"19.01.2013"},{"teams":["Wigan","Sunderland"],"score":[2,3],"koef":{"w1":2.13,"w2":3.28,"x":3.58},"date":"19.01.2013"},{"teams":["Chelsea","Southampton"],"score":[2,2],"koef":{"w1":1.22,"w2":6.57,"x":12.8},"date":"16.01.2013"},{"teams":["Arsenal","Manchester City"],"score":[0,2],"koef":{"w1":2.72,"w2":3.3,"x":2.61},"date":"13.01.2013"},{"teams":["Manchester United","Liverpool"],"score":[2,1],"koef":{"w1":1.96,"w2":3.48,"x":3.93},"date":"13.01.2013"},{"teams":["Aston Villa","Southampton"],"score":[0,1],"koef":{"w1":2.49,"w2":3.34,"x":2.82},"date":"12.01.2013"},{"teams":["Everton","Swansea"],"score":[0,0],"koef":{"w1":1.58,"w2":3.99,"x":5.84},"date":"12.01.2013"},{"teams":["Fulham","Wigan"],"score":[1,1],"koef":{"w1":2.04,"w2":3.38,"x":3.69},"date":"12.01.2013"},{"teams":["Norwich","Newcastle Utd"],"score":[0,0],"koef":{"w1":2.17,"w2":3.41,"x":3.32},"date":"12.01.2013"},{"teams":["QPR","Tottenham"],"score":[0,0],"koef":{"w1":4.53,"w2":3.67,"x":1.78},"date":"12.01.2013"},{"teams":["Reading","West Brom"],"score":[3,2],"koef":{"w1":2.82,"w2":3.3,"x":2.5},"date":"12.01.2013"},{"teams":["Stoke City","Chelsea"],"score":[0,4],"koef":{"w1":4.45,"w2":3.44,"x":1.86},"date":"12.01.2013"},{"teams":["Sunderland","West Ham"],"score":[3,0],"koef":{"w1":2.49,"w2":3.21,"x":2.94},"date":"12.01.2013"},{"teams":["Chelsea","QPR"],"score":[0,1],"koef":{"w1":1.25,"w2":5.98,"x":11.81},"date":"02.01.2013"},{"teams":["Liverpool","Sunderland"],"score":[3,0],"koef":{"w1":1.38,"w2":4.76,"x":8.37},"date":"02.01.2013"},{"teams":["Newcastle Utd","Everton"],"score":[1,2],"koef":{"w1":3.56,"w2":3.39,"x":2.09},"date":"02.01.2013"},{"teams":["Manchester City","Stoke City"],"score":[3,0],"koef":{"w1":1.32,"w2":4.98,"x":10.24},"date":"01.01.2013"},{"teams":["Southampton","Arsenal"],"score":[1,1],"koef":{"w1":4.87,"w2":3.81,"x":1.69},"date":"01.01.2013"},{"teams":["Swansea","Aston Villa"],"score":[2,2],"koef":{"w1":1.6,"w2":3.92,"x":5.72},"date":"01.01.2013"},{"teams":["Tottenham","Reading"],"score":[3,1],"koef":{"w1":1.33,"w2":4.97,"x":9.7},"date":"01.01.2013"},{"teams":["West Brom","Fulham"],"score":[1,2],"koef":{"w1":1.96,"w2":3.49,"x":3.85},"date":"01.01.2013"},{"teams":["West Ham","Norwich"],"score":[2,1],"koef":{"w1":1.98,"w2":3.42,"x":3.85},"date":"01.01.2013"},{"teams":["Wigan","Manchester United"],"score":[0,4],"koef":{"w1":5.01,"w2":3.77,"x":1.7},"date":"01.01.2013"},{"teams":["Everton","Chelsea"],"score":[1,2],"koef":{"w1":3.02,"w2":3.28,"x":2.37},"date":"30.12.2012"},{"teams":["QPR","Liverpool"],"score":[0,3],"koef":{"w1":4.33,"w2":3.63,"x":1.82},"date":"30.12.2012"},{"teams":["Arsenal","Newcastle Utd"],"score":[7,3],"koef":{"w1":1.42,"w2":4.57,"x":7.55},"date":"29.12.2012"},{"teams":["Aston Villa","Wigan"],"score":[0,3],"koef":{"w1":2.64,"w2":3.19,"x":2.78},"date":"29.12.2012"},{"teams":["Fulham","Swansea"],"score":[1,2],"koef":{"w1":2.19,"w2":3.33,"x":3.32},"date":"29.12.2012"},{"teams":["Manchester United","West Brom"],"score":[2,0],"koef":{"w1":1.3,"w2":5.46,"x":9.71},"date":"29.12.2012"},{"teams":["Norwich","Manchester City"],"score":[3,4],"koef":{"w1":6.14,"w2":4.05,"x":1.55},"date":"29.12.2012"},{"teams":["Reading","West Ham"],"score":[1,0],"koef":{"w1":2.76,"w2":3.27,"x":2.57},"date":"29.12.2012"},{"teams":["Stoke City","Southampton"],"score":[3,3],"koef":{"w1":1.92,"w2":3.32,"x":4.23},"date":"29.12.2012"},{"teams":["Sunderland","Tottenham"],"score":[1,2],"koef":{"w1":3.48,"w2":3.27,"x":2.16},"date":"29.12.2012"},{"teams":["Aston Villa","Tottenham"],"score":[0,4],"koef":{"w1":3.86,"w2":3.48,"x":1.95},"date":"26.12.2012"},{"teams":["Everton","Wigan"],"score":[2,1],"koef":{"w1":1.55,"w2":4,"x":6.26},"date":"26.12.2012"},{"teams":["Fulham","Southampton"],"score":[1,1],"koef":{"w1":1.89,"w2":3.5,"x":4.06},"date":"26.12.2012"},{"teams":["Manchester United","Newcastle Utd"],"score":[4,3],"koef":{"w1":1.25,"w2":5.94,"x":11.35},"date":"26.12.2012"},{"teams":["Norwich","Chelsea"],"score":[0,1],"koef":{"w1":5.45,"w2":3.83,"x":1.63},"date":"26.12.2012"},{"teams":["QPR","West Brom"],"score":[1,2],"koef":{"w1":2.31,"w2":3.35,"x":3.04},"date":"26.12.2012"},{"teams":["Reading","Swansea"],"score":[0,0],"koef":{"w1":2.89,"w2":3.31,"x":2.42},"date":"26.12.2012"},{"teams":["Stoke City","Liverpool"],"score":[3,1],"koef":{"w1":3.71,"w2":3.21,"x":2.1},"date":"26.12.2012"},{"teams":["Sunderland","Manchester City"],"score":[1,0],"koef":{"w1":6.48,"w2":4,"x":1.53},"date":"26.12.2012"},{"teams":["Chelsea","Aston Villa"],"score":[8,0],"koef":{"w1":1.34,"w2":5.13,"x":8.72},"date":"23.12.2012"},{"teams":["Swansea","Manchester United"],"score":[1,1],"koef":{"w1":4.94,"w2":3.79,"x":1.69},"date":"23.12.2012"},{"teams":["Liverpool","Fulham"],"score":[4,0],"koef":{"w1":1.47,"w2":4.26,"x":7.12},"date":"22.12.2012"},{"teams":["Manchester City","Reading"],"score":[1,0],"koef":{"w1":1.12,"w2":8.62,"x":18.13},"date":"22.12.2012"},{"teams":["Newcastle Utd","QPR"],"score":[1,0],"koef":{"w1":2.07,"w2":3.37,"x":3.61},"date":"22.12.2012"},{"teams":["Southampton","Sunderland"],"score":[0,1],"koef":{"w1":2.02,"w2":3.39,"x":3.72},"date":"22.12.2012"},{"teams":["Tottenham","Stoke City"],"score":[0,0],"koef":{"w1":1.61,"w2":3.72,"x":5.96},"date":"22.12.2012"},{"teams":["West Brom","Norwich"],"score":[2,1],"koef":{"w1":2.01,"w2":3.41,"x":3.76},"date":"22.12.2012"},{"teams":["West Ham","Everton"],"score":[1,2],"koef":{"w1":2.91,"w2":3.22,"x":2.48},"date":"22.12.2012"},{"teams":["Wigan","Arsenal"],"score":[0,1],"koef":{"w1":4.75,"w2":3.72,"x":1.72},"date":"22.12.2012"},{"teams":["Reading","Arsenal"],"score":[2,5],"koef":{"w1":5.55,"w2":4.01,"x":1.6},"date":"17.12.2012"},{"teams":["Tottenham","Swansea"],"score":[1,0],"koef":{"w1":1.65,"w2":3.84,"x":5.26},"date":"16.12.2012"},{"teams":["West Brom","West Ham"],"score":[0,0],"koef":{"w1":2,"w2":3.43,"x":3.73},"date":"16.12.2012"},{"teams":["Liverpool","Aston Villa"],"score":[1,3],"koef":{"w1":1.35,"w2":4.8,"x":9.06},"date":"15.12.2012"},{"teams":["Manchester United","Sunderland"],"score":[3,1],"koef":{"w1":1.2,"w2":6.54,"x":14.28},"date":"15.12.2012"},{"teams":["Newcastle Utd","Manchester City"],"score":[1,3],"koef":{"w1":5.33,"w2":3.91,"x":1.63},"date":"15.12.2012"},{"teams":["Norwich","Wigan"],"score":[2,1],"koef":{"w1":2.23,"w2":3.37,"x":3.18},"date":"15.12.2012"},{"teams":["QPR","Fulham"],"score":[2,1],"koef":{"w1":2.55,"w2":3.31,"x":2.75},"date":"15.12.2012"},{"teams":["Stoke City","Everton"],"score":[1,1],"koef":{"w1":3.1,"w2":3.13,"x":2.41},"date":"15.12.2012"},{"teams":["Sunderland","Reading"],"score":[3,0],"koef":{"w1":1.91,"w2":3.41,"x":4.18},"date":"11.12.2012"},{"teams":["Fulham","Newcastle Utd"],"score":[2,1],"koef":{"w1":2.02,"w2":3.47,"x":3.64},"date":"10.12.2012"},{"teams":["Everton","Tottenham"],"score":[2,1],"koef":{"w1":1.93,"w2":3.51,"x":3.93},"date":"09.12.2012"},{"teams":["Manchester City","Manchester United"],"score":[2,3],"koef":{"w1":2.13,"w2":3.38,"x":3.43},"date":"09.12.2012"},{"teams":["West Ham","Liverpool"],"score":[2,3],"koef":{"w1":3,"w2":3.22,"x":2.41},"date":"09.12.2012"},{"teams":["Arsenal","West Brom"],"score":[2,0],"koef":{"w1":1.55,"w2":3.98,"x":6.21},"date":"08.12.2012"},{"teams":["Aston Villa","Stoke City"],"score":[0,0],"koef":{"w1":2.61,"w2":3.09,"x":2.85},"date":"08.12.2012"},{"teams":["Southampton","Reading"],"score":[1,0],"koef":{"w1":1.89,"w2":3.61,"x":3.99},"date":"08.12.2012"},{"teams":["Sunderland","Chelsea"],"score":[1,3],"koef":{"w1":5.91,"w2":3.74,"x":1.62},"date":"08.12.2012"},{"teams":["Swansea","Norwich"],"score":[3,4],"koef":{"w1":1.71,"w2":3.72,"x":4.86},"date":"08.12.2012"},{"teams":["Wigan","QPR"],"score":[2,2],"koef":{"w1":2.19,"w2":3.44,"x":3.22},"date":"08.12.2012"},{"teams":["Newcastle Utd","Wigan"],"score":[3,0],"koef":{"w1":1.99,"w2":3.36,"x":3.87},"date":"03.12.2012"},{"teams":["Norwich","Sunderland"],"score":[2,1],"koef":{"w1":2.03,"w2":3.29,"x":3.79},"date":"02.12.2012"},{"teams":["Arsenal","Swansea"],"score":[0,2],"koef":{"w1":1.45,"w2":4.38,"x":7.19},"date":"01.12.2012"},{"teams":["Fulham","Tottenham"],"score":[0,3],"koef":{"w1":2.92,"w2":3.31,"x":2.41},"date":"01.12.2012"},{"teams":["Liverpool","Southampton"],"score":[1,0],"koef":{"w1":1.37,"w2":4.76,"x":8.57},"date":"01.12.2012"},{"teams":["Manchester City","Everton"],"score":[1,1],"koef":{"w1":1.54,"w2":4.03,"x":6.35},"date":"01.12.2012"},{"teams":["QPR","Aston Villa"],"score":[1,1],"koef":{"w1":1.97,"w2":3.42,"x":3.87},"date":"01.12.2012"},{"teams":["Reading","Manchester United"],"score":[3,4],"koef":{"w1":7.36,"w2":4.48,"x":1.43},"date":"01.12.2012"},{"teams":["West Brom","Stoke City"],"score":[0,1],"koef":{"w1":2.13,"w2":3.27,"x":3.52},"date":"01.12.2012"},{"teams":["West Ham","Chelsea"],"score":[3,1],"koef":{"w1":4.47,"w2":3.46,"x":1.85},"date":"01.12.2012"},{"teams":["Chelsea","Fulham"],"score":[0,0],"koef":{"w1":1.42,"w2":4.5,"x":7.53},"date":"28.11.2012"},{"teams":["Everton","Arsenal"],"score":[1,1],"koef":{"w1":2.44,"w2":3.38,"x":2.86},"date":"28.11.2012"},{"teams":["Manchester United","West Ham"],"score":[1,0],"koef":{"w1":1.24,"w2":6.14,"x":12.04},"date":"28.11.2012"},{"teams":["Southampton","Norwich"],"score":[1,1],"koef":{"w1":1.94,"w2":3.52,"x":3.88},"date":"28.11.2012"},{"teams":["Stoke City","Newcastle Utd"],"score":[2,1],"koef":{"w1":2.07,"w2":3.27,"x":3.74},"date":"28.11.2012"},{"teams":["Swansea","West Brom"],"score":[3,1],"koef":{"w1":2.25,"w2":3.38,"x":3.17},"date":"28.11.2012"},{"teams":["Tottenham","Liverpool"],"score":[2,1],"koef":{"w1":2.47,"w2":3.31,"x":2.88},"date":"28.11.2012"},{"teams":["Wigan","Manchester City"],"score":[0,2],"koef":{"w1":6.77,"w2":4.43,"x":1.47},"date":"28.11.2012"},{"teams":["Aston Villa","Reading"],"score":[1,0],"koef":{"w1":1.97,"w2":3.43,"x":3.85},"date":"27.11.2012"},{"teams":["Sunderland","QPR"],"score":[0,0],"koef":{"w1":2.33,"w2":3.23,"x":3.14},"date":"27.11.2012"},{"teams":["Chelsea","Manchester City"],"score":[0,0],"koef":{"w1":2.49,"w2":3.36,"x":2.79},"date":"25.11.2012"},{"teams":["Southampton","Newcastle Utd"],"score":[2,0],"koef":{"w1":2.09,"w2":3.48,"x":3.4},"date":"25.11.2012"},{"teams":["Swansea","Liverpool"],"score":[0,0],"koef":{"w1":3.54,"w2":3.39,"x":2.08},"date":"25.11.2012"},{"teams":["Tottenham","West Ham"],"score":[3,1],"koef":{"w1":1.69,"w2":3.69,"x":5.13},"date":"25.11.2012"},{"teams":["Aston Villa","Arsenal"],"score":[0,0],"koef":{"w1":4.53,"w2":3.68,"x":1.77},"date":"24.11.2012"},{"teams":["Everton","Norwich"],"score":[1,1],"koef":{"w1":1.48,"w2":4.26,"x":6.84},"date":"24.11.2012"},{"teams":["Manchester United","QPR"],"score":[3,1],"koef":{"w1":1.16,"w2":7.37,"x":15.28},"date":"24.11.2012"},{"teams":["Stoke City","Fulham"],"score":[1,0],"koef":{"w1":2.14,"w2":3.31,"x":3.45},"date":"24.11.2012"},{"teams":["Sunderland","West Brom"],"score":[2,4],"koef":{"w1":2.42,"w2":3.29,"x":2.94},"date":"24.11.2012"},{"teams":["Wigan","Reading"],"score":[3,2],"koef":{"w1":1.91,"w2":3.51,"x":4.02},"date":"24.11.2012"},{"teams":["West Ham","Stoke City"],"score":[1,1],"koef":{"w1":2.11,"w2":3.23,"x":3.64},"date":"19.11.2012"},{"teams":["Fulham","Sunderland"],"score":[1,3],"koef":{"w1":1.73,"w2":3.63,"x":4.91},"date":"18.11.2012"},{"teams":["Arsenal","Tottenham"],"score":[5,2],"koef":{"w1":1.95,"w2":3.56,"x":3.87},"date":"17.11.2012"},{"teams":["Liverpool","Wigan"],"score":[3,0],"koef":{"w1":1.45,"w2":4.34,"x":7.18},"date":"17.11.2012"},{"teams":["Manchester City","Aston Villa"],"score":[5,0],"koef":{"w1":1.2,"w2":6.57,"x":13.76},"date":"17.11.2012"},{"teams":["Newcastle Utd","Swansea"],"score":[1,2],"koef":{"w1":2.04,"w2":3.39,"x":3.69},"date":"17.11.2012"},{"teams":["Norwich","Manchester United"],"score":[1,0],"koef":{"w1":6.44,"w2":4.28,"x":1.5},"date":"17.11.2012"},{"teams":["QPR","Southampton"],"score":[1,3],"koef":{"w1":1.92,"w2":3.51,"x":3.92},"date":"17.11.2012"},{"teams":["Reading","Everton"],"score":[2,1],"koef":{"w1":4.38,"w2":3.66,"x":1.8},"date":"17.11.2012"},{"teams":["West Brom","Chelsea"],"score":[2,1],"koef":{"w1":3.59,"w2":3.48,"x":2.03},"date":"17.11.2012"},{"teams":["Chelsea","Liverpool"],"score":[1,1],"koef":{"w1":1.84,"w2":3.63,"x":4.18},"date":"11.11.2012"},{"teams":["Manchester City","Tottenham"],"score":[2,1],"koef":{"w1":1.51,"w2":4.38,"x":6.01},"date":"11.11.2012"},{"teams":["Newcastle Utd","West Ham"],"score":[0,1],"koef":{"w1":1.97,"w2":3.49,"x":3.79},"date":"11.11.2012"},{"teams":["Arsenal","Fulham"],"score":[3,3],"koef":{"w1":1.54,"w2":4.04,"x":6.2},"date":"10.11.2012"},{"teams":["Aston Villa","Manchester United"],"score":[2,3],"koef":{"w1":7.17,"w2":4.53,"x":1.43},"date":"10.11.2012"},{"teams":["Everton","Sunderland"],"score":[2,1],"koef":{"w1":1.41,"w2":4.4,"x":8.27},"date":"10.11.2012"},{"teams":["Reading","Norwich"],"score":[0,0],"koef":{"w1":2.25,"w2":3.37,"x":3.17},"date":"10.11.2012"},{"teams":["Southampton","Swansea"],"score":[1,1],"koef":{"w1":2.44,"w2":3.42,"x":2.82},"date":"10.11.2012"},{"teams":["Stoke City","QPR"],"score":[1,0],"koef":{"w1":1.96,"w2":3.36,"x":4},"date":"10.11.2012"},{"teams":["Wigan","West Brom"],"score":[1,2],"koef":{"w1":2.19,"w2":3.37,"x":3.3},"date":"10.11.2012"},{"teams":["West Brom","Southampton"],"score":[2,0],"koef":{"w1":1.81,"w2":3.65,"x":4.35},"date":"05.11.2012"},{"teams":["Liverpool","Newcastle Utd"],"score":[1,1],"koef":{"w1":1.6,"w2":4.12,"x":5.3},"date":"04.11.2012"},{"teams":["QPR","Reading"],"score":[1,1],"koef":{"w1":1.86,"w2":3.54,"x":4.16},"date":"04.11.2012"},{"teams":["Fulham","Everton"],"score":[2,2],"koef":{"w1":2.65,"w2":3.31,"x":2.62},"date":"03.11.2012"},{"teams":["Manchester United","Arsenal"],"score":[2,1],"koef":{"w1":1.7,"w2":3.81,"x":4.84},"date":"03.11.2012"},{"teams":["Norwich","Stoke City"],"score":[1,0],"koef":{"w1":2.48,"w2":3.22,"x":2.9},"date":"03.11.2012"},{"teams":["Sunderland","Aston Villa"],"score":[0,1],"koef":{"w1":2,"w2":3.29,"x":3.89},"date":"03.11.2012"},{"teams":["Swansea","Chelsea"],"score":[1,1],"koef":{"w1":4.27,"w2":3.63,"x":1.82},"date":"03.11.2012"},{"teams":["Tottenham","Wigan"],"score":[0,1],"koef":{"w1":1.47,"w2":4.25,"x":6.89},"date":"03.11.2012"},{"teams":["West Ham","Manchester City"],"score":[0,0],"koef":{"w1":4.85,"w2":3.81,"x":1.7},"date":"03.11.2012"},{"teams":["Chelsea","Manchester United"],"score":[2,3],"koef":{"w1":2.28,"w2":3.35,"x":3.11},"date":"28.10.2012"},{"teams":["Everton","Liverpool"],"score":[2,2],"koef":{"w1":2.61,"w2":3.19,"x":2.77},"date":"28.10.2012"},{"teams":["Newcastle Utd","West Brom"],"score":[2,1],"koef":{"w1":1.93,"w2":3.46,"x":3.95},"date":"28.10.2012"},{"teams":["Southampton","Tottenham"],"score":[1,2],"koef":{"w1":3.67,"w2":3.47,"x":2.01},"date":"28.10.2012"},{"teams":["Arsenal","QPR"],"score":[1,0],"koef":{"w1":1.36,"w2":4.81,"x":8.66},"date":"27.10.2012"},{"teams":["Aston Villa","Norwich"],"score":[1,1],"koef":{"w1":1.96,"w2":3.43,"x":3.91},"date":"27.10.2012"},{"teams":["Manchester City","Swansea"],"score":[1,0],"koef":{"w1":1.22,"w2":6.23,"x":13.02},"date":"27.10.2012"},{"teams":["Reading","Fulham"],"score":[3,3],"koef":{"w1":2.96,"w2":3.29,"x":2.4},"date":"27.10.2012"},{"teams":["Stoke City","Sunderland"],"score":[0,0],"koef":{"w1":1.93,"w2":3.32,"x":4.18},"date":"27.10.2012"},{"teams":["Wigan","West Ham"],"score":[2,1],"koef":{"w1":2.24,"w2":3.36,"x":3.17},"date":"27.10.2012"},{"teams":["QPR","Everton"],"score":[1,1],"koef":{"w1":3.39,"w2":3.39,"x":2.13},"date":"21.10.2012"},{"teams":["Sunderland","Newcastle Utd"],"score":[1,1],"koef":{"w1":2.77,"w2":3.17,"x":2.62},"date":"21.10.2012"},{"teams":["Fulham","Aston Villa"],"score":[1,0],"koef":{"w1":1.72,"w2":3.66,"x":4.98},"date":"20.10.2012"},{"teams":["Liverpool","Reading"],"score":[1,0],"koef":{"w1":1.31,"w2":5.13,"x":9.79},"date":"20.10.2012"},{"teams":["Manchester United","Stoke City"],"score":[4,2],"koef":{"w1":1.29,"w2":5.25,"x":10.78},"date":"20.10.2012"},{"teams":["Norwich","Arsenal"],"score":[1,0],"koef":{"w1":6.48,"w2":4.34,"x":1.48},"date":"20.10.2012"},{"teams":["Swansea","Wigan"],"score":[2,1],"koef":{"w1":2.08,"w2":3.38,"x":3.53},"date":"20.10.2012"},{"teams":["Tottenham","Chelsea"],"score":[2,4],"koef":{"w1":2.95,"w2":3.25,"x":2.45},"date":"20.10.2012"},{"teams":["West Brom","Manchester City"],"score":[1,2],"koef":{"w1":5.07,"w2":3.75,"x":1.68},"date":"20.10.2012"},{"teams":["West Ham","Southampton"],"score":[4,1],"koef":{"w1":1.83,"w2":3.62,"x":4.27},"date":"20.10.2012"},{"teams":["Liverpool","Stoke City"],"score":[0,0],"koef":{"w1":1.49,"w2":4.1,"x":7.06},"date":"07.10.2012"},{"teams":["Newcastle Utd","Manchester United"],"score":[0,3],"koef":{"w1":4.38,"w2":3.86,"x":1.76},"date":"07.10.2012"},{"teams":["Southampton","Fulham"],"score":[2,2],"koef":{"w1":2.53,"w2":3.32,"x":2.76},"date":"07.10.2012"},{"teams":["Tottenham","Aston Villa"],"score":[2,0],"koef":{"w1":1.45,"w2":4.29,"x":7.42},"date":"07.10.2012"},{"teams":["Chelsea","Norwich"],"score":[4,1],"koef":{"w1":1.21,"w2":6.34,"x":13.42},"date":"06.10.2012"},{"teams":["Manchester City","Sunderland"],"score":[3,0],"koef":{"w1":1.29,"w2":5.27,"x":11},"date":"06.10.2012"},{"teams":["Swansea","Reading"],"score":[2,2],"koef":{"w1":1.85,"w2":3.57,"x":4.22},"date":"06.10.2012"},{"teams":["West Brom","QPR"],"score":[3,2],"koef":{"w1":1.83,"w2":3.61,"x":4.25},"date":"06.10.2012"},{"teams":["West Ham","Arsenal"],"score":[1,3],"koef":{"w1":4.07,"w2":3.54,"x":1.88},"date":"06.10.2012"},{"teams":["Wigan","Everton"],"score":[2,2],"koef":{"w1":3.75,"w2":3.36,"x":2.02},"date":"06.10.2012"},{"teams":["QPR","West Ham"],"score":[1,2],"koef":{"w1":2.33,"w2":3.32,"x":3.06},"date":"01.10.2012"},{"teams":["Aston Villa","West Brom"],"score":[1,1],"koef":{"w1":2.47,"w2":3.27,"x":2.88},"date":"30.09.2012"},{"teams":["Arsenal","Chelsea"],"score":[1,2],"koef":{"w1":2.17,"w2":3.32,"x":3.38},"date":"29.09.2012"},{"teams":["Everton","Southampton"],"score":[3,1],"koef":{"w1":1.4,"w2":4.57,"x":7.98},"date":"29.09.2012"},{"teams":["Fulham","Manchester City"],"score":[1,2],"koef":{"w1":4.54,"w2":3.6,"x":1.78},"date":"29.09.2012"},{"teams":["Manchester United","Tottenham"],"score":[2,3],"koef":{"w1":1.54,"w2":4.1,"x":6.12},"date":"29.09.2012"},{"teams":["Norwich","Liverpool"],"score":[2,5],"koef":{"w1":4.57,"w2":3.62,"x":1.78},"date":"29.09.2012"},{"teams":["Reading","Newcastle Utd"],"score":[2,2],"koef":{"w1":2.71,"w2":3.28,"x":2.59},"date":"29.09.2012"},{"teams":["Stoke City","Swansea"],"score":[2,0],"koef":{"w1":1.94,"w2":3.39,"x":4.03},"date":"29.09.2012"},{"teams":["Sunderland","Wigan"],"score":[1,0],"koef":{"w1":2.11,"w2":3.28,"x":3.56},"date":"29.09.2012"},{"teams":["Liverpool","Manchester United"],"score":[1,2],"koef":{"w1":2.7,"w2":3.19,"x":2.68},"date":"23.09.2012"},{"teams":["Manchester City","Arsenal"],"score":[1,1],"koef":{"w1":1.75,"w2":3.74,"x":4.61},"date":"23.09.2012"},{"teams":["Newcastle Utd","Norwich"],"score":[1,0],"koef":{"w1":1.71,"w2":3.76,"x":4.83},"date":"23.09.2012"},{"teams":["Tottenham","QPR"],"score":[2,1],"koef":{"w1":1.49,"w2":4.2,"x":6.86},"date":"23.09.2012"},{"teams":["Chelsea","Stoke City"],"score":[1,0],"koef":{"w1":1.37,"w2":4.61,"x":8.93},"date":"22.09.2012"},{"teams":["Southampton","Aston Villa"],"score":[4,1],"koef":{"w1":2.29,"w2":3.3,"x":3.16},"date":"22.09.2012"},{"teams":["Swansea","Everton"],"score":[0,3],"koef":{"w1":3.13,"w2":3.25,"x":2.33},"date":"22.09.2012"},{"teams":["West Brom","Reading"],"score":[1,0],"koef":{"w1":1.64,"w2":3.82,"x":5.38},"date":"22.09.2012"},{"teams":["West Ham","Sunderland"],"score":[1,1],"koef":{"w1":2,"w2":3.32,"x":3.89},"date":"22.09.2012"},{"teams":["Wigan","Fulham"],"score":[1,2],"koef":{"w1":2.38,"w2":3.26,"x":3},"date":"22.09.2012"},{"teams":["Everton","Newcastle Utd"],"score":[2,2],"koef":{"w1":1.55,"w2":4.01,"x":6.08},"date":"17.09.2012"},{"teams":["Reading","Tottenham"],"score":[1,3],"koef":{"w1":3.66,"w2":3.38,"x":2.04},"date":"16.09.2012"},{"teams":["Arsenal","Southampton"],"score":[6,1],"koef":{"w1":1.34,"w2":4.94,"x":9.18},"date":"15.09.2012"},{"teams":["Aston Villa","Swansea"],"score":[2,0],"koef":{"w1":2.31,"w2":3.25,"x":3.14},"date":"15.09.2012"},{"teams":["Fulham","West Brom"],"score":[3,0],"koef":{"w1":2.11,"w2":3.31,"x":3.53},"date":"15.09.2012"},{"teams":["Manchester United","Wigan"],"score":[4,0],"koef":{"w1":1.27,"w2":5.55,"x":11.44},"date":"15.09.2012"},{"teams":["Norwich","West Ham"],"score":[0,0],"koef":{"w1":2.42,"w2":3.27,"x":2.95},"date":"15.09.2012"},{"teams":["QPR","Chelsea"],"score":[0,0],"koef":{"w1":4.38,"w2":3.5,"x":1.84},"date":"15.09.2012"},{"teams":["Stoke City","Manchester City"],"score":[1,1],"koef":{"w1":5.26,"w2":3.63,"x":1.69},"date":"15.09.2012"},{"teams":["Sunderland","Liverpool"],"score":[1,1],"koef":{"w1":3.49,"w2":3.36,"x":2.1},"date":"15.09.2012"},{"teams":["Liverpool","Arsenal"],"score":[0,2],"koef":{"w1":1.93,"w2":3.46,"x":4.04},"date":"02.09.2012"},{"teams":["Newcastle Utd","Aston Villa"],"score":[1,1],"koef":{"w1":1.65,"w2":3.73,"x":5.47},"date":"02.09.2012"},{"teams":["Southampton","Manchester United"],"score":[2,3],"koef":{"w1":6.63,"w2":4.21,"x":1.49},"date":"02.09.2012"},{"teams":["Manchester City","QPR"],"score":[3,1],"koef":{"w1":1.18,"w2":6.98,"x":14.54},"date":"01.09.2012"},{"teams":["Swansea","Sunderland"],"score":[2,2],"koef":{"w1":2.03,"w2":3.37,"x":3.72},"date":"01.09.2012"},{"teams":["Tottenham","Norwich"],"score":[1,1],"koef":{"w1":1.36,"w2":4.83,"x":8.48},"date":"01.09.2012"},{"teams":["West Brom","Everton"],"score":[2,0],"koef":{"w1":3.03,"w2":3.28,"x":2.37},"date":"01.09.2012"},{"teams":["West Ham","Fulham"],"score":[3,0],"koef":{"w1":2.53,"w2":3.28,"x":2.79},"date":"01.09.2012"},{"teams":["Wigan","Stoke City"],"score":[2,2],"koef":{"w1":2.12,"w2":3.25,"x":3.59},"date":"01.09.2012"},{"teams":["Liverpool","Manchester City"],"score":[2,2],"koef":{"w1":2.89,"w2":3.27,"x":2.44},"date":"26.08.2012"},{"teams":["Stoke City","Arsenal"],"score":[0,0],"koef":{"w1":3.21,"w2":3.27,"x":2.26},"date":"26.08.2012"},{"teams":["Aston Villa","Everton"],"score":[1,3],"koef":{"w1":3.24,"w2":3.27,"x":2.26},"date":"25.08.2012"},{"teams":["Chelsea","Newcastle Utd"],"score":[2,0],"koef":{"w1":1.47,"w2":4.29,"x":6.89},"date":"25.08.2012"},{"teams":["Manchester United","Fulham"],"score":[3,2],"koef":{"w1":1.29,"w2":5.28,"x":10.8},"date":"25.08.2012"},{"teams":["Norwich","QPR"],"score":[1,1],"koef":{"w1":2.32,"w2":3.34,"x":3.03},"date":"25.08.2012"},{"teams":["Southampton","Wigan"],"score":[0,2],"koef":{"w1":2.13,"w2":3.35,"x":3.45},"date":"25.08.2012"},{"teams":["Swansea","West Ham"],"score":[3,0],"koef":{"w1":2.12,"w2":3.31,"x":3.52},"date":"25.08.2012"},{"teams":["Tottenham","West Brom"],"score":[1,1],"koef":{"w1":1.56,"w2":3.96,"x":6.03},"date":"25.08.2012"},{"teams":["Chelsea","Reading"],"score":[4,2],"koef":{"w1":1.27,"w2":5.49,"x":11.4},"date":"22.08.2012"},{"teams":["Everton","Manchester United"],"score":[1,0],"koef":{"w1":3.83,"w2":3.46,"x":1.97},"date":"20.08.2012"},{"teams":["Manchester City","Southampton"],"score":[3,2],"koef":{"w1":1.15,"w2":7.67,"x":17.82},"date":"19.08.2012"},{"teams":["Wigan","Chelsea"],"score":[0,2],"koef":{"w1":4.86,"w2":3.52,"x":1.75},"date":"19.08.2012"},{"teams":["Arsenal","Sunderland"],"score":[0,0],"koef":{"w1":1.43,"w2":4.38,"x":7.81},"date":"18.08.2012"},{"teams":["Fulham","Norwich"],"score":[5,0],"koef":{"w1":1.79,"w2":3.59,"x":4.53},"date":"18.08.2012"},{"teams":["Newcastle Utd","Tottenham"],"score":[2,1],"koef":{"w1":2.68,"w2":3.28,"x":2.63},"date":"18.08.2012"},{"teams":["QPR","Swansea"],"score":[0,5],"koef":{"w1":1.95,"w2":3.39,"x":3.99},"date":"18.08.2012"},{"teams":["Reading","Stoke City"],"score":[1,1],"koef":{"w1":2.37,"w2":3.24,"x":3.05},"date":"18.08.2012"},{"teams":["West Brom","Liverpool"],"score":[3,0],"koef":{"w1":4.44,"w2":3.49,"x":1.83},"date":"18.08.2012"},{"teams":["West Ham","Aston Villa"],"score":[1,0],"koef":{"w1":2.11,"w2":3.37,"x":3.46},"date":"18.08.2012"}]